[
    {
        "title": "에필로그",
        "url": "https://www.lezhin.com/ko/comic/sleepingman/235",
        "imageUrl": "https://ccdn.lezhin.com/v2/comics/5551016703033344/episodes/5226070810624000/images/cover.jpg",
        "publicationDate": "24.01.27"
    },
    {
        "title": "에필로그",
        "url": "https://www.lezhin.com/ko/comic/sleepingman/234",
        "imageUrl": "https://ccdn.lezhin.com/v2/comics/5551016703033344/episodes/6282673829773312/images/cover.jpg",
        "publicationDate": "24.01.20"
    },
    {
        "title": "에필로그",
        "url": "https://www.lezhin.com/ko/comic/sleepingman/233",
        "imageUrl": "https://ccdn.lezhin.com/v2/comics/5551016703033344/episodes/6674866713198592/images/cover.jpg",
        "publicationDate": "24.01.13"
    },
    {
        "title": "에필로그",
        "url": "https://www.lezhin.com/ko/comic/sleepingman/232",
        "imageUrl": "https://ccdn.lezhin.com/v2/comics/5551016703033344/episodes/6279469842890752/images/cover.jpg",
        "publicationDate": "24.01.06"
    },
    {
        "title": "에필로그",
        "url": "https://www.lezhin.com/ko/comic/sleepingman/231",
        "imageUrl": "https://ccdn.lezhin.com/v2/comics/5551016703033344/episodes/6418449968201728/images/cover.jpg",
        "publicationDate": "23.12.30"
    },
    {
        "title": "푸앙카레",
        "url": "https://www.lezhin.com/ko/comic/sleepingman/230",
        "imageUrl": "https://ccdn.lezhin.com/v2/comics/5551016703033344/episodes/5689379408117760/images/cover.jpg",
        "publicationDate": "23.12.23"
    },
    {
        "title": "구골플렉스",
        "url": "https://www.lezhin.com/ko/comic/sleepingman/229",
        "imageUrl": "https://ccdn.lezhin.com/v2/comics/5551016703033344/episodes/5860435213221888/images/cover.jpg",
        "publicationDate": "23.12.16"
    },
    {
        "title": "구골플렉스",
        "url": "https://www.lezhin.com/ko/comic/sleepingman/228",
        "imageUrl": "https://ccdn.lezhin.com/v2/comics/5551016703033344/episodes/6694868690468864/images/cover.jpg",
        "publicationDate": "23.12.09"
    },
    {
        "title": "불가설불가설전",
        "url": "https://www.lezhin.com/ko/comic/sleepingman/227",
        "imageUrl": "https://ccdn.lezhin.com/v2/comics/5551016703033344/episodes/6082918428246016/images/cover.jpg",
        "publicationDate": "23.12.02"
    },
    {
        "title": "불가설불가설전",
        "url": "https://www.lezhin.com/ko/comic/sleepingman/226",
        "imageUrl": "https://ccdn.lezhin.com/v2/comics/5551016703033344/episodes/5834701913522176/images/cover.jpg",
        "publicationDate": "23.11.25"
    },
    {
        "title": "나유타",
        "url": "https://www.lezhin.com/ko/comic/sleepingman/225",
        "imageUrl": "https://ccdn.lezhin.com/v2/comics/5551016703033344/episodes/5908692321763328/images/cover.jpg",
        "publicationDate": "23.11.18"
    },
    {
        "title": "나유타",
        "url": "https://www.lezhin.com/ko/comic/sleepingman/224",
        "imageUrl": "https://ccdn.lezhin.com/v2/comics/5551016703033344/episodes/5837618296979456/images/cover.jpg",
        "publicationDate": "23.11.11"
    },
    {
        "title": "67,108,864일 후",
        "url": "https://www.lezhin.com/ko/comic/sleepingman/223",
        "imageUrl": "https://ccdn.lezhin.com/v2/comics/5551016703033344/episodes/5915141424873472/images/cover.jpg",
        "publicationDate": "23.11.04"
    },
    {
        "title": "33,554,432일 후",
        "url": "https://www.lezhin.com/ko/comic/sleepingman/222",
        "imageUrl": "https://ccdn.lezhin.com/v2/comics/5551016703033344/episodes/6416801892990976/images/cover.jpg",
        "publicationDate": "23.10.28"
    },
    {
        "title": "33,554,432일 후",
        "url": "https://www.lezhin.com/ko/comic/sleepingman/221",
        "imageUrl": "https://ccdn.lezhin.com/v2/comics/5551016703033344/episodes/5493468011757568/images/cover.jpg",
        "publicationDate": "23.10.21"
    },
    {
        "title": "33,554,432일 후",
        "url": "https://www.lezhin.com/ko/comic/sleepingman/220",
        "imageUrl": "https://ccdn.lezhin.com/v2/comics/5551016703033344/episodes/5719349200224256/images/cover.jpg",
        "publicationDate": "23.10.14"
    },
    {
        "title": "33,554,432일 후",
        "url": "https://www.lezhin.com/ko/comic/sleepingman/219",
        "imageUrl": "https://ccdn.lezhin.com/v2/comics/5551016703033344/episodes/5991280675717120/images/cover.jpg",
        "publicationDate": "23.10.07"
    },
    {
        "title": "16,777,216일 후",
        "url": "https://www.lezhin.com/ko/comic/sleepingman/218",
        "imageUrl": "https://ccdn.lezhin.com/v2/comics/5551016703033344/episodes/6549816543608832/images/cover.jpg",
        "publicationDate": "23.09.23"
    },
    {
        "title": "16,777,216일 후",
        "url": "https://www.lezhin.com/ko/comic/sleepingman/217",
        "imageUrl": "https://ccdn.lezhin.com/v2/comics/5551016703033344/episodes/5058844483715072/images/cover.jpg",
        "publicationDate": "23.09.16"
    },
    {
        "title": "16,777,216일 후",
        "url": "https://www.lezhin.com/ko/comic/sleepingman/216",
        "imageUrl": "https://ccdn.lezhin.com/v2/comics/5551016703033344/episodes/6018950385958912/images/cover.jpg",
        "publicationDate": "23.09.09"
    },
    {
        "title": "8,388,608일 후",
        "url": "https://www.lezhin.com/ko/comic/sleepingman/215",
        "imageUrl": "https://ccdn.lezhin.com/v2/comics/5551016703033344/episodes/6594038353166336/images/cover.jpg",
        "publicationDate": "23.09.02"
    },
    {
        "title": "8,388,608일 후",
        "url": "https://www.lezhin.com/ko/comic/sleepingman/214",
        "imageUrl": "https://ccdn.lezhin.com/v2/comics/5551016703033344/episodes/5315283462717440/images/cover.jpg",
        "publicationDate": "23.08.26"
    },
    {
        "title": "8,388,608일 후",
        "url": "https://www.lezhin.com/ko/comic/sleepingman/213",
        "imageUrl": "https://ccdn.lezhin.com/v2/comics/5551016703033344/episodes/5343833385402368/images/cover.jpg",
        "publicationDate": "23.08.19"
    },
    {
        "title": "8,388,608일 후",
        "url": "https://www.lezhin.com/ko/comic/sleepingman/212",
        "imageUrl": "https://ccdn.lezhin.com/v2/comics/5551016703033344/episodes/6496274545967104/images/cover.jpg",
        "publicationDate": "23.08.12"
    },
    {
        "title": "8,388,608일 후",
        "url": "https://www.lezhin.com/ko/comic/sleepingman/211",
        "imageUrl": "https://ccdn.lezhin.com/v2/comics/5551016703033344/episodes/5515579606499328/images/cover.jpg",
        "publicationDate": "23.08.05"
    },
    {
        "title": "8,388,608일 후",
        "url": "https://www.lezhin.com/ko/comic/sleepingman/210",
        "imageUrl": "https://ccdn.lezhin.com/v2/comics/5551016703033344/episodes/5197318595608576/images/cover.jpg",
        "publicationDate": "23.07.29"
    },
    {
        "title": "8,388,608일 후",
        "url": "https://www.lezhin.com/ko/comic/sleepingman/209",
        "imageUrl": "https://ccdn.lezhin.com/v2/comics/5551016703033344/episodes/6731836666216448/images/cover.jpg",
        "publicationDate": "23.07.22"
    },
    {
        "title": "8,388,608일 후",
        "url": "https://www.lezhin.com/ko/comic/sleepingman/208",
        "imageUrl": "https://ccdn.lezhin.com/v2/comics/5551016703033344/episodes/5441733918523392/images/cover.jpg",
        "publicationDate": "23.07.15"
    },
    {
        "title": "4,194,304일 후",
        "url": "https://www.lezhin.com/ko/comic/sleepingman/207",
        "imageUrl": "https://ccdn.lezhin.com/v2/comics/5551016703033344/episodes/6287807394676736/images/cover.jpg",
        "publicationDate": "23.07.08"
    },
    {
        "title": "4,194,304일 후",
        "url": "https://www.lezhin.com/ko/comic/sleepingman/206",
        "imageUrl": "https://ccdn.lezhin.com/v2/comics/5551016703033344/episodes/5107336600158208/images/cover.jpg",
        "publicationDate": "23.07.01"
    },
    {
        "title": "4,194,304일 후",
        "url": "https://www.lezhin.com/ko/comic/sleepingman/205",
        "imageUrl": "https://ccdn.lezhin.com/v2/comics/5551016703033344/episodes/6509777640030208/images/cover.jpg",
        "publicationDate": "23.06.24"
    },
    {
        "title": "4,194,304일 후",
        "url": "https://www.lezhin.com/ko/comic/sleepingman/204",
        "imageUrl": "https://ccdn.lezhin.com/v2/comics/5551016703033344/episodes/5194129097949184/images/cover.jpg",
        "publicationDate": "23.06.17"
    },
    {
        "title": "2,097,152일 후",
        "url": "https://www.lezhin.com/ko/comic/sleepingman/203",
        "imageUrl": "https://ccdn.lezhin.com/v2/comics/5551016703033344/episodes/4630761559621632/images/cover.jpg",
        "publicationDate": "23.06.10"
    },
    {
        "title": "2,097,152일 후 : 7부 1화",
        "url": "https://www.lezhin.com/ko/comic/sleepingman/202",
        "imageUrl": "https://ccdn.lezhin.com/v2/comics/5551016703033344/episodes/5021124786978816/images/cover.jpg",
        "publicationDate": "23.06.03"
    },
    {
        "title": "6부 후기",
        "url": "https://www.lezhin.com/ko/comic/sleepingman/e6",
        "imageUrl": "https://ccdn.lezhin.com/v2/comics/5551016703033344/episodes/6738869425602560/images/cover.jpg",
        "publicationDate": "23.03.04"
    },
    {
        "title": "1,048,576일 후",
        "url": "https://www.lezhin.com/ko/comic/sleepingman/201",
        "imageUrl": "https://ccdn.lezhin.com/v2/comics/5551016703033344/episodes/6650188652150784/images/cover.jpg",
        "publicationDate": "23.05.27"
    },
    {
        "title": "1,048,576일 후",
        "url": "https://www.lezhin.com/ko/comic/sleepingman/200",
        "imageUrl": "https://ccdn.lezhin.com/v2/comics/5551016703033344/episodes/5080010202087424/images/cover.jpg",
        "publicationDate": "23.05.20"
    },
    {
        "title": "1,048,576일 후",
        "url": "https://www.lezhin.com/ko/comic/sleepingman/199",
        "imageUrl": "https://ccdn.lezhin.com/v2/comics/5551016703033344/episodes/5029590138159104/images/cover.jpg",
        "publicationDate": "23.05.13"
    },
    {
        "title": "1,048,576일 후",
        "url": "https://www.lezhin.com/ko/comic/sleepingman/198",
        "imageUrl": "https://ccdn.lezhin.com/v2/comics/5551016703033344/episodes/5254872380014592/images/cover.jpg",
        "publicationDate": "23.05.06"
    },
    {
        "title": "1,048,576일 후",
        "url": "https://www.lezhin.com/ko/comic/sleepingman/197",
        "imageUrl": "https://ccdn.lezhin.com/v2/comics/5551016703033344/episodes/5312455962853376/images/cover.jpg",
        "publicationDate": "23.04.29"
    },
    {
        "title": "1,048,576일 후",
        "url": "https://www.lezhin.com/ko/comic/sleepingman/196",
        "imageUrl": "https://ccdn.lezhin.com/v2/comics/5551016703033344/episodes/5804051376439296/images/cover.jpg",
        "publicationDate": "23.04.22"
    },
    {
        "title": "1,048,576일 후",
        "url": "https://www.lezhin.com/ko/comic/sleepingman/195",
        "imageUrl": "https://ccdn.lezhin.com/v2/comics/5551016703033344/episodes/6383120417619968/images/cover.jpg",
        "publicationDate": "23.04.15"
    },
    {
        "title": "1,048,576일 후",
        "url": "https://www.lezhin.com/ko/comic/sleepingman/194",
        "imageUrl": "https://ccdn.lezhin.com/v2/comics/5551016703033344/episodes/6445293558890496/images/cover.jpg",
        "publicationDate": "23.04.08"
    },
    {
        "title": "1,048,576일 후",
        "url": "https://www.lezhin.com/ko/comic/sleepingman/193",
        "imageUrl": "https://ccdn.lezhin.com/v2/comics/5551016703033344/episodes/5947097216778240/images/cover.jpg",
        "publicationDate": "23.04.01"
    },
    {
        "title": "1,048,576일 후",
        "url": "https://www.lezhin.com/ko/comic/sleepingman/192",
        "imageUrl": "https://ccdn.lezhin.com/v2/comics/5551016703033344/episodes/5612017508220928/images/cover.jpg",
        "publicationDate": "23.03.25"
    },
    {
        "title": "1,048,576일 후",
        "url": "https://www.lezhin.com/ko/comic/sleepingman/191",
        "imageUrl": "https://ccdn.lezhin.com/v2/comics/5551016703033344/episodes/5586665121579008/images/cover.jpg",
        "publicationDate": "23.02.25"
    },
    {
        "title": "524,288일 후",
        "url": "https://www.lezhin.com/ko/comic/sleepingman/190",
        "imageUrl": "https://ccdn.lezhin.com/v2/comics/5551016703033344/episodes/5060249200164864/images/cover.jpg",
        "publicationDate": "23.02.18"
    },
    {
        "title": "262144일 후",
        "url": "https://www.lezhin.com/ko/comic/sleepingman/189",
        "imageUrl": "https://ccdn.lezhin.com/v2/comics/5551016703033344/episodes/6492578112143360/images/cover.jpg",
        "publicationDate": "23.02.11"
    },
    {
        "title": "262144일 후",
        "url": "https://www.lezhin.com/ko/comic/sleepingman/188",
        "imageUrl": "https://ccdn.lezhin.com/v2/comics/5551016703033344/episodes/4706621390127104/images/cover.jpg",
        "publicationDate": "23.02.04"
    },
    {
        "title": "262144일 후",
        "url": "https://www.lezhin.com/ko/comic/sleepingman/187",
        "imageUrl": "https://ccdn.lezhin.com/v2/comics/5551016703033344/episodes/4991280479535104/images/cover.jpg",
        "publicationDate": "23.01.28"
    },
    {
        "title": "262144일 후",
        "url": "https://www.lezhin.com/ko/comic/sleepingman/186",
        "imageUrl": "https://ccdn.lezhin.com/v2/comics/5551016703033344/episodes/4689635262660608/images/cover.jpg",
        "publicationDate": "23.01.21"
    },
    {
        "title": "131072일 후",
        "url": "https://www.lezhin.com/ko/comic/sleepingman/185",
        "imageUrl": "https://ccdn.lezhin.com/v2/comics/5551016703033344/episodes/6174277262180352/images/cover.jpg",
        "publicationDate": "23.01.07"
    },
    {
        "title": "131072일 후",
        "url": "https://www.lezhin.com/ko/comic/sleepingman/184",
        "imageUrl": "https://ccdn.lezhin.com/v2/comics/5551016703033344/episodes/4935059676397568/images/cover.jpg",
        "publicationDate": "22.12.31"
    },
    {
        "title": "131072일 후",
        "url": "https://www.lezhin.com/ko/comic/sleepingman/183",
        "imageUrl": "https://ccdn.lezhin.com/v2/comics/5551016703033344/episodes/5384135064748032/images/cover.jpg",
        "publicationDate": "22.12.24"
    },
    {
        "title": "131072일 후",
        "url": "https://www.lezhin.com/ko/comic/sleepingman/182",
        "imageUrl": "https://ccdn.lezhin.com/v2/comics/5551016703033344/episodes/6713077856010240/images/cover.jpg",
        "publicationDate": "22.12.17"
    },
    {
        "title": "131072일 후",
        "url": "https://www.lezhin.com/ko/comic/sleepingman/181",
        "imageUrl": "https://ccdn.lezhin.com/v2/comics/5551016703033344/episodes/6715182264156160/images/cover.jpg",
        "publicationDate": "22.12.10"
    },
    {
        "title": "131072일 후",
        "url": "https://www.lezhin.com/ko/comic/sleepingman/180",
        "imageUrl": "https://ccdn.lezhin.com/v2/comics/5551016703033344/episodes/5090191420489728/images/cover.jpg",
        "publicationDate": "22.12.03"
    },
    {
        "title": "131072일 후",
        "url": "https://www.lezhin.com/ko/comic/sleepingman/179",
        "imageUrl": "https://ccdn.lezhin.com/v2/comics/5551016703033344/episodes/5834301483843584/images/cover.jpg",
        "publicationDate": "22.11.26"
    },
    {
        "title": "131072일 후",
        "url": "https://www.lezhin.com/ko/comic/sleepingman/178",
        "imageUrl": "https://ccdn.lezhin.com/v2/comics/5551016703033344/episodes/5727973444747264/images/cover.jpg",
        "publicationDate": "22.11.19"
    },
    {
        "title": "131072일 후",
        "url": "https://www.lezhin.com/ko/comic/sleepingman/177",
        "imageUrl": "https://ccdn.lezhin.com/v2/comics/5551016703033344/episodes/6231781010636800/images/cover.jpg",
        "publicationDate": "22.11.12"
    },
    {
        "title": "131072일 후",
        "url": "https://www.lezhin.com/ko/comic/sleepingman/176",
        "imageUrl": "https://ccdn.lezhin.com/v2/comics/5551016703033344/episodes/5940639203393536/images/cover.jpg",
        "publicationDate": "22.11.05"
    },
    {
        "title": "131072일 후",
        "url": "https://www.lezhin.com/ko/comic/sleepingman/175",
        "imageUrl": "https://ccdn.lezhin.com/v2/comics/5551016703033344/episodes/5083726051868672/images/cover.jpg",
        "publicationDate": "22.10.29"
    },
    {
        "title": "65536일 후",
        "url": "https://www.lezhin.com/ko/comic/sleepingman/174",
        "imageUrl": "https://ccdn.lezhin.com/v2/comics/5551016703033344/episodes/6680254180818944/images/cover.jpg",
        "publicationDate": "22.10.22"
    },
    {
        "title": "65536일 후",
        "url": "https://www.lezhin.com/ko/comic/sleepingman/173",
        "imageUrl": "https://ccdn.lezhin.com/v2/comics/5551016703033344/episodes/5517009617223680/images/cover.jpg",
        "publicationDate": "22.10.15"
    },
    {
        "title": "65536일 후",
        "url": "https://www.lezhin.com/ko/comic/sleepingman/172",
        "imageUrl": "https://ccdn.lezhin.com/v2/comics/5551016703033344/episodes/4819076290772992/images/cover.jpg",
        "publicationDate": "22.10.08"
    },
    {
        "title": "65536일 후",
        "url": "https://www.lezhin.com/ko/comic/sleepingman/171",
        "imageUrl": "https://ccdn.lezhin.com/v2/comics/5551016703033344/episodes/4586175766790144/images/cover.jpg",
        "publicationDate": "22.10.01"
    },
    {
        "title": "65536일 후",
        "url": "https://www.lezhin.com/ko/comic/sleepingman/170",
        "imageUrl": "https://ccdn.lezhin.com/v2/comics/5551016703033344/episodes/5669098804805632/images/cover.jpg",
        "publicationDate": "22.09.24"
    },
    {
        "title": "65536일 후",
        "url": "https://www.lezhin.com/ko/comic/sleepingman/169",
        "imageUrl": "https://ccdn.lezhin.com/v2/comics/5551016703033344/episodes/6474603412389888/images/cover.jpg",
        "publicationDate": "22.09.17"
    },
    {
        "title": "65536일 후",
        "url": "https://www.lezhin.com/ko/comic/sleepingman/168",
        "imageUrl": "https://ccdn.lezhin.com/v2/comics/5551016703033344/episodes/5536131235250176/images/cover.jpg",
        "publicationDate": "22.09.03"
    },
    {
        "title": "65536일 후",
        "url": "https://www.lezhin.com/ko/comic/sleepingman/167",
        "imageUrl": "https://ccdn.lezhin.com/v2/comics/5551016703033344/episodes/5373210509246464/images/cover.jpg",
        "publicationDate": "22.08.27"
    },
    {
        "title": "65536일 후",
        "url": "https://www.lezhin.com/ko/comic/sleepingman/166",
        "imageUrl": "https://ccdn.lezhin.com/v2/comics/5551016703033344/episodes/5713365644410880/images/cover.jpg",
        "publicationDate": "22.08.20"
    },
    {
        "title": "65536일 후",
        "url": "https://www.lezhin.com/ko/comic/sleepingman/165",
        "imageUrl": "https://ccdn.lezhin.com/v2/comics/5551016703033344/episodes/5815642321387520/images/cover.jpg",
        "publicationDate": "22.08.13"
    },
    {
        "title": "65536일 후",
        "url": "https://www.lezhin.com/ko/comic/sleepingman/164",
        "imageUrl": "https://ccdn.lezhin.com/v2/comics/5551016703033344/episodes/5963967070797824/images/cover.jpg",
        "publicationDate": "22.08.06"
    },
    {
        "title": "65536일 후",
        "url": "https://www.lezhin.com/ko/comic/sleepingman/163",
        "imageUrl": "https://ccdn.lezhin.com/v2/comics/5551016703033344/episodes/4689814187474944/images/cover.jpg",
        "publicationDate": "22.07.30"
    },
    {
        "title": "65536일 후",
        "url": "https://www.lezhin.com/ko/comic/sleepingman/162",
        "imageUrl": "https://ccdn.lezhin.com/v2/comics/5551016703033344/episodes/5690686522589184/images/cover.jpg",
        "publicationDate": "22.07.23"
    },
    {
        "title": "65536일 후",
        "url": "https://www.lezhin.com/ko/comic/sleepingman/161",
        "imageUrl": "https://ccdn.lezhin.com/v2/comics/5551016703033344/episodes/4802853767282688/images/cover.jpg",
        "publicationDate": "22.07.16"
    },
    {
        "title": "65536일 후",
        "url": "https://www.lezhin.com/ko/comic/sleepingman/160",
        "imageUrl": "https://ccdn.lezhin.com/v2/comics/5551016703033344/episodes/5723348582858752/images/cover.jpg",
        "publicationDate": "22.07.09"
    },
    {
        "title": "65536일 후",
        "url": "https://www.lezhin.com/ko/comic/sleepingman/159",
        "imageUrl": "https://ccdn.lezhin.com/v2/comics/5551016703033344/episodes/5213074121621504/images/cover.jpg",
        "publicationDate": "22.07.02"
    },
    {
        "title": "65536일 후 : 6부 1화",
        "url": "https://www.lezhin.com/ko/comic/sleepingman/158",
        "imageUrl": "https://ccdn.lezhin.com/v2/comics/5551016703033344/episodes/6392750676443136/images/cover.jpg",
        "publicationDate": "22.06.25"
    },
    {
        "title": "5부 후기",
        "url": "https://www.lezhin.com/ko/comic/sleepingman/e5",
        "imageUrl": "https://ccdn.lezhin.com/v2/comics/5551016703033344/episodes/4752126537695232/images/cover.jpg",
        "publicationDate": "22.03.26"
    },
    {
        "title": "32768일 후",
        "url": "https://www.lezhin.com/ko/comic/sleepingman/157",
        "imageUrl": "https://ccdn.lezhin.com/v2/comics/5551016703033344/episodes/4616970460004352/images/cover.jpg",
        "publicationDate": "22.06.18"
    },
    {
        "title": "32768일 후",
        "url": "https://www.lezhin.com/ko/comic/sleepingman/156",
        "imageUrl": "https://ccdn.lezhin.com/v2/comics/5551016703033344/episodes/4898169680101376/images/cover.jpg",
        "publicationDate": "22.06.11"
    },
    {
        "title": "32768일 후",
        "url": "https://www.lezhin.com/ko/comic/sleepingman/155",
        "imageUrl": "https://ccdn.lezhin.com/v2/comics/5551016703033344/episodes/5720086236430336/images/cover.jpg",
        "publicationDate": "22.06.04"
    },
    {
        "title": "32768일 후",
        "url": "https://www.lezhin.com/ko/comic/sleepingman/154",
        "imageUrl": "https://ccdn.lezhin.com/v2/comics/5551016703033344/episodes/4678156088049664/images/cover.jpg",
        "publicationDate": "22.05.21"
    },
    {
        "title": "32768일 후",
        "url": "https://www.lezhin.com/ko/comic/sleepingman/153",
        "imageUrl": "https://ccdn.lezhin.com/v2/comics/5551016703033344/episodes/4541827081633792/images/cover.jpg",
        "publicationDate": "22.05.14"
    },
    {
        "title": "32768일 후",
        "url": "https://www.lezhin.com/ko/comic/sleepingman/152",
        "imageUrl": "https://ccdn.lezhin.com/v2/comics/5551016703033344/episodes/5308020893745152/images/cover.jpg",
        "publicationDate": "22.05.07"
    },
    {
        "title": "32768일 후",
        "url": "https://www.lezhin.com/ko/comic/sleepingman/151",
        "imageUrl": "https://ccdn.lezhin.com/v2/comics/5551016703033344/episodes/5851331220013056/images/cover.jpg",
        "publicationDate": "22.04.30"
    },
    {
        "title": "32768일 후",
        "url": "https://www.lezhin.com/ko/comic/sleepingman/150",
        "imageUrl": "https://ccdn.lezhin.com/v2/comics/5551016703033344/episodes/5376070607241216/images/cover.jpg",
        "publicationDate": "22.04.23"
    },
    {
        "title": "32768일 후",
        "url": "https://www.lezhin.com/ko/comic/sleepingman/149",
        "imageUrl": "https://ccdn.lezhin.com/v2/comics/5551016703033344/episodes/4757904218718208/images/cover.jpg",
        "publicationDate": "22.04.16"
    },
    {
        "title": "32768일 후",
        "url": "https://www.lezhin.com/ko/comic/sleepingman/148",
        "imageUrl": "https://ccdn.lezhin.com/v2/comics/5551016703033344/episodes/5400788043366400/images/cover.jpg",
        "publicationDate": "22.04.09"
    },
    {
        "title": "32768일 후",
        "url": "https://www.lezhin.com/ko/comic/sleepingman/147",
        "imageUrl": "https://ccdn.lezhin.com/v2/comics/5551016703033344/episodes/5269138814861312/images/cover.jpg",
        "publicationDate": "22.03.19"
    },
    {
        "title": "32768일 후",
        "url": "https://www.lezhin.com/ko/comic/sleepingman/146",
        "imageUrl": "https://ccdn.lezhin.com/v2/comics/5551016703033344/episodes/5992569776701440/images/cover.jpg",
        "publicationDate": "22.03.12"
    },
    {
        "title": "32768일 후",
        "url": "https://www.lezhin.com/ko/comic/sleepingman/145",
        "imageUrl": "https://ccdn.lezhin.com/v2/comics/5551016703033344/episodes/4880701502849024/images/cover.jpg",
        "publicationDate": "22.03.05"
    },
    {
        "title": "32768일 후",
        "url": "https://www.lezhin.com/ko/comic/sleepingman/144",
        "imageUrl": "https://ccdn.lezhin.com/v2/comics/5551016703033344/episodes/5627432326725632/images/cover.jpg",
        "publicationDate": "22.02.26"
    },
    {
        "title": "32768일 후",
        "url": "https://www.lezhin.com/ko/comic/sleepingman/143",
        "imageUrl": "https://ccdn.lezhin.com/v2/comics/5551016703033344/episodes/6721558141009920/images/cover.jpg",
        "publicationDate": "22.02.19"
    },
    {
        "title": "32768일 후",
        "url": "https://www.lezhin.com/ko/comic/sleepingman/142",
        "imageUrl": "https://ccdn.lezhin.com/v2/comics/5551016703033344/episodes/5979061777399808/images/cover.jpg",
        "publicationDate": "22.02.12"
    },
    {
        "title": "32768일 후",
        "url": "https://www.lezhin.com/ko/comic/sleepingman/141",
        "imageUrl": "https://ccdn.lezhin.com/v2/comics/5551016703033344/episodes/6448264607236096/images/cover.jpg",
        "publicationDate": "22.02.05"
    },
    {
        "title": "32768일 후",
        "url": "https://www.lezhin.com/ko/comic/sleepingman/140",
        "imageUrl": "https://ccdn.lezhin.com/v2/comics/5551016703033344/episodes/5630810410778624/images/cover.jpg",
        "publicationDate": "22.01.29"
    },
    {
        "title": "32768일 후",
        "url": "https://www.lezhin.com/ko/comic/sleepingman/139",
        "imageUrl": "https://ccdn.lezhin.com/v2/comics/5551016703033344/episodes/5655234413395968/images/cover.jpg",
        "publicationDate": "22.01.22"
    },
    {
        "title": "32768일 후",
        "url": "https://www.lezhin.com/ko/comic/sleepingman/138",
        "imageUrl": "https://ccdn.lezhin.com/v2/comics/5551016703033344/episodes/4979888034742272/images/cover.jpg",
        "publicationDate": "22.01.15"
    },
    {
        "title": "32768일 후",
        "url": "https://www.lezhin.com/ko/comic/sleepingman/137",
        "imageUrl": "https://ccdn.lezhin.com/v2/comics/5551016703033344/episodes/6458646348496896/images/cover.jpg",
        "publicationDate": "22.01.08"
    },
    {
        "title": "32768일 후",
        "url": "https://www.lezhin.com/ko/comic/sleepingman/136",
        "imageUrl": "https://ccdn.lezhin.com/v2/comics/5551016703033344/episodes/5307482772930560/images/cover.jpg",
        "publicationDate": "22.01.01"
    },
    {
        "title": "32768일 후 : 5부 1화",
        "url": "https://www.lezhin.com/ko/comic/sleepingman/135",
        "imageUrl": "https://ccdn.lezhin.com/v2/comics/5551016703033344/episodes/4967554448949248/images/cover.jpg",
        "publicationDate": "21.12.25"
    },
    {
        "title": "4부 후기",
        "url": "https://www.lezhin.com/ko/comic/sleepingman/e4",
        "imageUrl": "https://ccdn.lezhin.com/v2/comics/5551016703033344/episodes/5462867995590656/images/cover.jpg",
        "publicationDate": "21.09.25"
    },
    {
        "title": "16384일 후",
        "url": "https://www.lezhin.com/ko/comic/sleepingman/134",
        "imageUrl": "https://ccdn.lezhin.com/v2/comics/5551016703033344/episodes/5002273152630784/images/cover.jpg",
        "publicationDate": "21.12.18"
    },
    {
        "title": "16384일 후",
        "url": "https://www.lezhin.com/ko/comic/sleepingman/133",
        "imageUrl": "https://ccdn.lezhin.com/v2/comics/5551016703033344/episodes/5715612224782336/images/cover.jpg",
        "publicationDate": "21.12.11"
    },
    {
        "title": "16384일 후",
        "url": "https://www.lezhin.com/ko/comic/sleepingman/132",
        "imageUrl": "https://ccdn.lezhin.com/v2/comics/5551016703033344/episodes/4639572324843520/images/cover.jpg",
        "publicationDate": "21.12.04"
    },
    {
        "title": "16384일 후",
        "url": "https://www.lezhin.com/ko/comic/sleepingman/131",
        "imageUrl": "https://ccdn.lezhin.com/v2/comics/5551016703033344/episodes/6080994051686400/images/cover.jpg",
        "publicationDate": "21.11.27"
    },
    {
        "title": "16384일 후",
        "url": "https://www.lezhin.com/ko/comic/sleepingman/130",
        "imageUrl": "https://ccdn.lezhin.com/v2/comics/5551016703033344/episodes/4691322977189888/images/cover.jpg",
        "publicationDate": "21.11.20"
    },
    {
        "title": "16384일 후2",
        "url": "https://www.lezhin.com/ko/comic/sleepingman/129",
        "imageUrl": "https://ccdn.lezhin.com/v2/comics/5551016703033344/episodes/4637757499834368/images/cover.jpg",
        "publicationDate": "21.11.13"
    },
    {
        "title": "16384일 후",
        "url": "https://www.lezhin.com/ko/comic/sleepingman/128",
        "imageUrl": "https://ccdn.lezhin.com/v2/comics/5551016703033344/episodes/4523651950247936/images/cover.jpg",
        "publicationDate": "21.11.06"
    },
    {
        "title": "16384일 후",
        "url": "https://www.lezhin.com/ko/comic/sleepingman/127",
        "imageUrl": "https://ccdn.lezhin.com/v2/comics/5551016703033344/episodes/5941394347982848/images/cover.jpg",
        "publicationDate": "21.10.23"
    },
    {
        "title": "16384일 후",
        "url": "https://www.lezhin.com/ko/comic/sleepingman/126",
        "imageUrl": "https://ccdn.lezhin.com/v2/comics/5551016703033344/episodes/5434062643986432/images/cover.jpg",
        "publicationDate": "21.10.16"
    },
    {
        "title": "16384일 후",
        "url": "https://www.lezhin.com/ko/comic/sleepingman/125",
        "imageUrl": "https://ccdn.lezhin.com/v2/comics/5551016703033344/episodes/5598697598812160/images/cover.jpg",
        "publicationDate": "21.10.09"
    },
    {
        "title": "16384일 후",
        "url": "https://www.lezhin.com/ko/comic/sleepingman/124",
        "imageUrl": "https://ccdn.lezhin.com/v2/comics/5551016703033344/episodes/5853910746333184/images/cover.jpg",
        "publicationDate": "21.09.18"
    },
    {
        "title": "16384일 후",
        "url": "https://www.lezhin.com/ko/comic/sleepingman/123",
        "imageUrl": "https://ccdn.lezhin.com/v2/comics/5551016703033344/episodes/5278511427551232/images/cover.jpg",
        "publicationDate": "21.09.11"
    },
    {
        "title": "16384일 후",
        "url": "https://www.lezhin.com/ko/comic/sleepingman/122",
        "imageUrl": "https://ccdn.lezhin.com/v2/comics/5551016703033344/episodes/5462343879557120/images/cover.jpg",
        "publicationDate": "21.09.04"
    },
    {
        "title": "16384일 후",
        "url": "https://www.lezhin.com/ko/comic/sleepingman/121",
        "imageUrl": "https://ccdn.lezhin.com/v2/comics/5551016703033344/episodes/6518449770921984/images/cover.jpg",
        "publicationDate": "21.08.28"
    },
    {
        "title": "16384일 후",
        "url": "https://www.lezhin.com/ko/comic/sleepingman/120",
        "imageUrl": "https://ccdn.lezhin.com/v2/comics/5551016703033344/episodes/5477716515422208/images/cover.jpg",
        "publicationDate": "21.08.21"
    },
    {
        "title": "16384일 후",
        "url": "https://www.lezhin.com/ko/comic/sleepingman/119",
        "imageUrl": "https://ccdn.lezhin.com/v2/comics/5551016703033344/episodes/6650817424982016/images/cover.jpg",
        "publicationDate": "21.08.14"
    },
    {
        "title": "16384일 후",
        "url": "https://www.lezhin.com/ko/comic/sleepingman/118",
        "imageUrl": "https://ccdn.lezhin.com/v2/comics/5551016703033344/episodes/4744484614373376/images/cover.jpg",
        "publicationDate": "21.08.07"
    },
    {
        "title": "16384일 후",
        "url": "https://www.lezhin.com/ko/comic/sleepingman/117",
        "imageUrl": "https://ccdn.lezhin.com/v2/comics/5551016703033344/episodes/4652511678234624/images/cover.jpg",
        "publicationDate": "21.07.31"
    },
    {
        "title": "16384일 후",
        "url": "https://www.lezhin.com/ko/comic/sleepingman/116",
        "imageUrl": "https://ccdn.lezhin.com/v2/comics/5551016703033344/episodes/6121590830202880/images/cover.jpg",
        "publicationDate": "21.07.24"
    },
    {
        "title": "16384일 후",
        "url": "https://www.lezhin.com/ko/comic/sleepingman/115",
        "imageUrl": "https://ccdn.lezhin.com/v2/comics/5551016703033344/episodes/6497460069662720/images/cover.jpg",
        "publicationDate": "21.07.10"
    },
    {
        "title": "16384일 후",
        "url": "https://www.lezhin.com/ko/comic/sleepingman/114",
        "imageUrl": "https://ccdn.lezhin.com/v2/comics/5551016703033344/episodes/6366108695461888/images/cover.jpg",
        "publicationDate": "21.07.03"
    },
    {
        "title": "????",
        "url": "https://www.lezhin.com/ko/comic/sleepingman/113",
        "imageUrl": "https://ccdn.lezhin.com/v2/comics/5551016703033344/episodes/6167943719485440/images/cover.jpg",
        "publicationDate": "21.06.26"
    },
    {
        "title": "8192일 후",
        "url": "https://www.lezhin.com/ko/comic/sleepingman/112",
        "imageUrl": "https://ccdn.lezhin.com/v2/comics/5551016703033344/episodes/6579904433160192/images/cover.jpg",
        "publicationDate": "21.06.19"
    },
    {
        "title": "8192일 후",
        "url": "https://www.lezhin.com/ko/comic/sleepingman/111",
        "imageUrl": "https://ccdn.lezhin.com/v2/comics/5551016703033344/episodes/6582021550047232/images/cover.jpg",
        "publicationDate": "21.06.12"
    },
    {
        "title": "8192일 후",
        "url": "https://www.lezhin.com/ko/comic/sleepingman/110",
        "imageUrl": "https://ccdn.lezhin.com/v2/comics/5551016703033344/episodes/6315084387516416/images/cover.jpg",
        "publicationDate": "21.06.05"
    },
    {
        "title": "8192일 후",
        "url": "https://www.lezhin.com/ko/comic/sleepingman/109",
        "imageUrl": "https://ccdn.lezhin.com/v2/comics/5551016703033344/episodes/6227633333665792/images/cover.jpg",
        "publicationDate": "21.05.29"
    },
    {
        "title": "8192일 후",
        "url": "https://www.lezhin.com/ko/comic/sleepingman/108",
        "imageUrl": "https://ccdn.lezhin.com/v2/comics/5551016703033344/episodes/6143358097752064/images/cover.jpg",
        "publicationDate": "21.05.22"
    },
    {
        "title": "8192일 후",
        "url": "https://www.lezhin.com/ko/comic/sleepingman/107",
        "imageUrl": "https://ccdn.lezhin.com/v2/comics/5551016703033344/episodes/5173891838574592/images/cover.jpg",
        "publicationDate": "21.05.15"
    },
    {
        "title": "8192일 후",
        "url": "https://www.lezhin.com/ko/comic/sleepingman/106",
        "imageUrl": "https://ccdn.lezhin.com/v2/comics/5551016703033344/episodes/6639668798226432/images/cover.jpg",
        "publicationDate": "21.05.08"
    },
    {
        "title": "8192일 후",
        "url": "https://www.lezhin.com/ko/comic/sleepingman/105",
        "imageUrl": "https://ccdn.lezhin.com/v2/comics/5551016703033344/episodes/5829608465563648/images/cover.jpg",
        "publicationDate": "21.05.01"
    },
    {
        "title": "8192일 후",
        "url": "https://www.lezhin.com/ko/comic/sleepingman/104",
        "imageUrl": "https://ccdn.lezhin.com/v2/comics/5551016703033344/episodes/6348021503950848/images/cover.jpg",
        "publicationDate": "21.04.24"
    },
    {
        "title": "8192일 후",
        "url": "https://www.lezhin.com/ko/comic/sleepingman/103",
        "imageUrl": "https://ccdn.lezhin.com/v2/comics/5551016703033344/episodes/5095176330870784/images/cover.jpg",
        "publicationDate": "21.04.17"
    },
    {
        "title": "8192일 후",
        "url": "https://www.lezhin.com/ko/comic/sleepingman/102",
        "imageUrl": "https://ccdn.lezhin.com/v2/comics/5551016703033344/episodes/4729759020154880/images/cover.jpg",
        "publicationDate": "21.04.10"
    },
    {
        "title": "8192일 후",
        "url": "https://www.lezhin.com/ko/comic/sleepingman/101",
        "imageUrl": "https://ccdn.lezhin.com/v2/comics/5551016703033344/episodes/5350157147504640/images/cover.jpg",
        "publicationDate": "21.04.03"
    },
    {
        "title": "8192일 후 : 4부 1화",
        "url": "https://www.lezhin.com/ko/comic/sleepingman/100",
        "imageUrl": "https://ccdn.lezhin.com/v2/comics/5551016703033344/episodes/5463714879045632/images/cover.jpg",
        "publicationDate": "21.03.27"
    },
    {
        "title": "3부 후기",
        "url": "https://www.lezhin.com/ko/comic/sleepingman/e3",
        "imageUrl": "https://ccdn.lezhin.com/v2/comics/5551016703033344/episodes/6198517156085760/images/cover.jpg",
        "publicationDate": "20.11.21"
    },
    {
        "title": "4096일 후 : 3부 최종화",
        "url": "https://www.lezhin.com/ko/comic/sleepingman/99",
        "imageUrl": "https://ccdn.lezhin.com/v2/comics/5551016703033344/episodes/6094376194867200/images/cover.jpg",
        "publicationDate": "21.03.13"
    },
    {
        "title": "4096일 후",
        "url": "https://www.lezhin.com/ko/comic/sleepingman/98",
        "imageUrl": "https://ccdn.lezhin.com/v2/comics/5551016703033344/episodes/4795914176233472/images/cover.jpg",
        "publicationDate": "21.03.06"
    },
    {
        "title": "4096일 후",
        "url": "https://www.lezhin.com/ko/comic/sleepingman/97",
        "imageUrl": "https://ccdn.lezhin.com/v2/comics/5551016703033344/episodes/6539982291927040/images/cover.jpg",
        "publicationDate": "21.02.27"
    },
    {
        "title": "4096일 후",
        "url": "https://www.lezhin.com/ko/comic/sleepingman/96",
        "imageUrl": "https://ccdn.lezhin.com/v2/comics/5551016703033344/episodes/5902990977859584/images/cover.jpg",
        "publicationDate": "21.02.20"
    },
    {
        "title": "4096일 후",
        "url": "https://www.lezhin.com/ko/comic/sleepingman/95",
        "imageUrl": "https://ccdn.lezhin.com/v2/comics/5551016703033344/episodes/6657061577883648/images/cover.jpg",
        "publicationDate": "21.02.13"
    },
    {
        "title": "4096일 후",
        "url": "https://www.lezhin.com/ko/comic/sleepingman/94",
        "imageUrl": "https://ccdn.lezhin.com/v2/comics/5551016703033344/episodes/5905033943646208/images/cover.jpg",
        "publicationDate": "21.02.06"
    },
    {
        "title": "4096일 후",
        "url": "https://www.lezhin.com/ko/comic/sleepingman/93",
        "imageUrl": "https://ccdn.lezhin.com/v2/comics/5551016703033344/episodes/5332275501268992/images/cover.jpg",
        "publicationDate": "21.01.30"
    },
    {
        "title": "4096일 후",
        "url": "https://www.lezhin.com/ko/comic/sleepingman/92",
        "imageUrl": "https://ccdn.lezhin.com/v2/comics/5551016703033344/episodes/5009629119053824/images/cover.jpg",
        "publicationDate": "21.01.23"
    },
    {
        "title": "4096일 후",
        "url": "https://www.lezhin.com/ko/comic/sleepingman/91",
        "imageUrl": "https://ccdn.lezhin.com/v2/comics/5551016703033344/episodes/4517634907897856/images/cover.jpg",
        "publicationDate": "21.01.16"
    },
    {
        "title": "4096일 후",
        "url": "https://www.lezhin.com/ko/comic/sleepingman/90",
        "imageUrl": "https://ccdn.lezhin.com/v2/comics/5551016703033344/episodes/5741060184145920/images/cover.jpg",
        "publicationDate": "21.01.09"
    },
    {
        "title": "4096일 후",
        "url": "https://www.lezhin.com/ko/comic/sleepingman/89",
        "imageUrl": "https://ccdn.lezhin.com/v2/comics/5551016703033344/episodes/6217088430047232/images/cover.jpg",
        "publicationDate": "20.11.14"
    },
    {
        "title": "4096일 후",
        "url": "https://www.lezhin.com/ko/comic/sleepingman/88",
        "imageUrl": "https://ccdn.lezhin.com/v2/comics/5551016703033344/episodes/4912379052228608/images/cover.jpg",
        "publicationDate": "20.11.07"
    },
    {
        "title": "4096일 후",
        "url": "https://www.lezhin.com/ko/comic/sleepingman/87",
        "imageUrl": "https://ccdn.lezhin.com/v2/comics/5551016703033344/episodes/4829304825905152/images/cover.jpg",
        "publicationDate": "20.10.31"
    },
    {
        "title": "2048일 후",
        "url": "https://www.lezhin.com/ko/comic/sleepingman/86",
        "imageUrl": "https://ccdn.lezhin.com/v2/comics/5551016703033344/episodes/5830876577988608/images/cover.jpg",
        "publicationDate": "20.10.24"
    },
    {
        "title": "2048일 후",
        "url": "https://www.lezhin.com/ko/comic/sleepingman/85",
        "imageUrl": "https://ccdn.lezhin.com/v2/comics/5551016703033344/episodes/5866806563110912/images/cover.jpg",
        "publicationDate": "20.10.17"
    },
    {
        "title": "2048일 후",
        "url": "https://www.lezhin.com/ko/comic/sleepingman/84",
        "imageUrl": "https://ccdn.lezhin.com/v2/comics/5551016703033344/episodes/5982168522752000/images/cover.jpg",
        "publicationDate": "20.10.10"
    },
    {
        "title": "2048일 후",
        "url": "https://www.lezhin.com/ko/comic/sleepingman/83",
        "imageUrl": "https://ccdn.lezhin.com/v2/comics/5551016703033344/episodes/5400991223054336/images/cover.jpg",
        "publicationDate": "20.10.03"
    },
    {
        "title": "2048일 후",
        "url": "https://www.lezhin.com/ko/comic/sleepingman/82",
        "imageUrl": "https://ccdn.lezhin.com/v2/comics/5551016703033344/episodes/6385533975068672/images/cover.jpg",
        "publicationDate": "20.09.26"
    },
    {
        "title": "2048일 후",
        "url": "https://www.lezhin.com/ko/comic/sleepingman/81",
        "imageUrl": "https://ccdn.lezhin.com/v2/comics/5551016703033344/episodes/5784479646416896/images/cover.jpg",
        "publicationDate": "20.09.19"
    },
    {
        "title": "2048일 후",
        "url": "https://www.lezhin.com/ko/comic/sleepingman/80",
        "imageUrl": "https://ccdn.lezhin.com/v2/comics/5551016703033344/episodes/6736980617003008/images/cover.jpg",
        "publicationDate": "20.09.12"
    },
    {
        "title": "2048일 후",
        "url": "https://www.lezhin.com/ko/comic/sleepingman/79",
        "imageUrl": "https://ccdn.lezhin.com/v2/comics/5551016703033344/episodes/6088761008521216/images/cover.jpg",
        "publicationDate": "20.09.05"
    },
    {
        "title": "1024일 후",
        "url": "https://www.lezhin.com/ko/comic/sleepingman/78",
        "imageUrl": "https://ccdn.lezhin.com/v2/comics/5551016703033344/episodes/6459299898392576/images/cover.jpg",
        "publicationDate": "20.08.29"
    },
    {
        "title": "1024일 후",
        "url": "https://www.lezhin.com/ko/comic/sleepingman/77",
        "imageUrl": "https://ccdn.lezhin.com/v2/comics/5551016703033344/episodes/6032476987260928/images/cover.jpg",
        "publicationDate": "20.08.22"
    },
    {
        "title": "1024일 후",
        "url": "https://www.lezhin.com/ko/comic/sleepingman/76",
        "imageUrl": "https://ccdn.lezhin.com/v2/comics/5551016703033344/episodes/5839658423484416/images/cover.jpg",
        "publicationDate": "20.08.15"
    },
    {
        "title": "1024일 후",
        "url": "https://www.lezhin.com/ko/comic/sleepingman/75",
        "imageUrl": "https://ccdn.lezhin.com/v2/comics/5551016703033344/episodes/5895535763456000/images/cover.jpg",
        "publicationDate": "20.08.08"
    },
    {
        "title": "1024일 후",
        "url": "https://www.lezhin.com/ko/comic/sleepingman/74",
        "imageUrl": "https://ccdn.lezhin.com/v2/comics/5551016703033344/episodes/4600497662132224/images/cover.jpg",
        "publicationDate": "20.08.01"
    },
    {
        "title": "1024일 후",
        "url": "https://www.lezhin.com/ko/comic/sleepingman/73",
        "imageUrl": "https://ccdn.lezhin.com/v2/comics/5551016703033344/episodes/4888250849230848/images/cover.jpg",
        "publicationDate": "20.07.25"
    },
    {
        "title": "1024일 후 : 3부 1화",
        "url": "https://www.lezhin.com/ko/comic/sleepingman/72",
        "imageUrl": "https://ccdn.lezhin.com/v2/comics/5551016703033344/episodes/6108919444340736/images/cover.jpg",
        "publicationDate": "20.07.18"
    },
    {
        "title": "2부 후기",
        "url": "https://www.lezhin.com/ko/comic/sleepingman/e2",
        "imageUrl": "https://ccdn.lezhin.com/v2/comics/5551016703033344/episodes/6337657041911808/images/cover.jpg",
        "publicationDate": "20.04.11"
    },
    {
        "title": "1024일 후 : 2부 최종화",
        "url": "https://www.lezhin.com/ko/comic/sleepingman/71",
        "imageUrl": "https://ccdn.lezhin.com/v2/comics/5551016703033344/episodes/5051143183990784/images/cover.jpg",
        "publicationDate": "20.07.11"
    },
    {
        "title": "512일 후",
        "url": "https://www.lezhin.com/ko/comic/sleepingman/70",
        "imageUrl": "https://ccdn.lezhin.com/v2/comics/5551016703033344/episodes/6326299395162112/images/cover.jpg",
        "publicationDate": "20.07.04"
    },
    {
        "title": "512일 후",
        "url": "https://www.lezhin.com/ko/comic/sleepingman/69",
        "imageUrl": "https://ccdn.lezhin.com/v2/comics/5551016703033344/episodes/6670425221300224/images/cover.jpg",
        "publicationDate": "20.06.27"
    },
    {
        "title": "512일 후",
        "url": "https://www.lezhin.com/ko/comic/sleepingman/68",
        "imageUrl": "https://ccdn.lezhin.com/v2/comics/5551016703033344/episodes/5349350793347072/images/cover.jpg",
        "publicationDate": "20.06.20"
    },
    {
        "title": "512일 후",
        "url": "https://www.lezhin.com/ko/comic/sleepingman/67",
        "imageUrl": "https://ccdn.lezhin.com/v2/comics/5551016703033344/episodes/5353360195649536/images/cover.jpg",
        "publicationDate": "20.06.13"
    },
    {
        "title": "512일 후",
        "url": "https://www.lezhin.com/ko/comic/sleepingman/66",
        "imageUrl": "https://ccdn.lezhin.com/v2/comics/5551016703033344/episodes/5624204482379776/images/cover.jpg",
        "publicationDate": "20.06.06"
    },
    {
        "title": "512일 후",
        "url": "https://www.lezhin.com/ko/comic/sleepingman/65",
        "imageUrl": "https://ccdn.lezhin.com/v2/comics/5551016703033344/episodes/4770644513325056/images/cover.jpg",
        "publicationDate": "20.05.30"
    },
    {
        "title": "512일 후",
        "url": "https://www.lezhin.com/ko/comic/sleepingman/64",
        "imageUrl": "https://ccdn.lezhin.com/v2/comics/5551016703033344/episodes/6560450314567680/images/cover.jpg",
        "publicationDate": "20.05.23"
    },
    {
        "title": "512일 후",
        "url": "https://www.lezhin.com/ko/comic/sleepingman/63",
        "imageUrl": "https://ccdn.lezhin.com/v2/comics/5551016703033344/episodes/5018092301254656/images/cover.jpg",
        "publicationDate": "20.05.16"
    },
    {
        "title": "512일 후",
        "url": "https://www.lezhin.com/ko/comic/sleepingman/62",
        "imageUrl": "https://ccdn.lezhin.com/v2/comics/5551016703033344/episodes/5990165018378240/images/cover.jpg",
        "publicationDate": "20.05.09"
    },
    {
        "title": "512일 후",
        "url": "https://www.lezhin.com/ko/comic/sleepingman/61",
        "imageUrl": "https://ccdn.lezhin.com/v2/comics/5551016703033344/episodes/5264235179343872/images/cover.jpg",
        "publicationDate": "20.04.04"
    },
    {
        "title": "512일 후",
        "url": "https://www.lezhin.com/ko/comic/sleepingman/60",
        "imageUrl": "https://ccdn.lezhin.com/v2/comics/5551016703033344/episodes/6629185902673920/images/cover.jpg",
        "publicationDate": "20.03.28"
    },
    {
        "title": "256일 후",
        "url": "https://www.lezhin.com/ko/comic/sleepingman/59",
        "imageUrl": "https://ccdn.lezhin.com/v2/comics/5551016703033344/episodes/5322522130186240/images/cover.jpg",
        "publicationDate": "20.03.21"
    },
    {
        "title": "256일 후",
        "url": "https://www.lezhin.com/ko/comic/sleepingman/58",
        "imageUrl": "https://ccdn.lezhin.com/v2/comics/5551016703033344/episodes/5699241051750400/images/cover.jpg",
        "publicationDate": "20.03.14"
    },
    {
        "title": "256일 후",
        "url": "https://www.lezhin.com/ko/comic/sleepingman/57",
        "imageUrl": "https://ccdn.lezhin.com/v2/comics/5551016703033344/episodes/4883421329424384/images/cover.jpg",
        "publicationDate": "20.03.07"
    },
    {
        "title": "256일 후",
        "url": "https://www.lezhin.com/ko/comic/sleepingman/56",
        "imageUrl": "https://ccdn.lezhin.com/v2/comics/5551016703033344/episodes/5802671896330240/images/cover.jpg",
        "publicationDate": "20.02.29"
    },
    {
        "title": "256일 후",
        "url": "https://www.lezhin.com/ko/comic/sleepingman/55",
        "imageUrl": "https://ccdn.lezhin.com/v2/comics/5551016703033344/episodes/6470174282678272/images/cover.jpg",
        "publicationDate": "20.02.22"
    },
    {
        "title": "256일 후",
        "url": "https://www.lezhin.com/ko/comic/sleepingman/54",
        "imageUrl": "https://ccdn.lezhin.com/v2/comics/5551016703033344/episodes/6739903849234432/images/cover.jpg",
        "publicationDate": "20.02.15"
    },
    {
        "title": "128일 후",
        "url": "https://www.lezhin.com/ko/comic/sleepingman/53",
        "imageUrl": "https://ccdn.lezhin.com/v2/comics/5551016703033344/episodes/5070588917907456/images/cover.jpg",
        "publicationDate": "20.02.08"
    },
    {
        "title": "128일 후",
        "url": "https://www.lezhin.com/ko/comic/sleepingman/52",
        "imageUrl": "https://ccdn.lezhin.com/v2/comics/5551016703033344/episodes/4646805753102336/images/cover.jpg",
        "publicationDate": "20.02.01"
    },
    {
        "title": "128일 후",
        "url": "https://www.lezhin.com/ko/comic/sleepingman/51",
        "imageUrl": "https://ccdn.lezhin.com/v2/comics/5551016703033344/episodes/6549721715900416/images/cover.jpg",
        "publicationDate": "20.01.25"
    },
    {
        "title": "128일 후",
        "url": "https://www.lezhin.com/ko/comic/sleepingman/50",
        "imageUrl": "https://ccdn.lezhin.com/v2/comics/5551016703033344/episodes/5928324907991040/images/cover.jpg",
        "publicationDate": "20.01.18"
    },
    {
        "title": "128일 후",
        "url": "https://www.lezhin.com/ko/comic/sleepingman/49",
        "imageUrl": "https://ccdn.lezhin.com/v2/comics/5551016703033344/episodes/5135047220854784/images/cover.jpg",
        "publicationDate": "20.01.11"
    },
    {
        "title": "128일 후",
        "url": "https://www.lezhin.com/ko/comic/sleepingman/48",
        "imageUrl": "https://ccdn.lezhin.com/v2/comics/5551016703033344/episodes/5540698694680576/images/cover.jpg",
        "publicationDate": "20.01.04"
    },
    {
        "title": "128일 후",
        "url": "https://www.lezhin.com/ko/comic/sleepingman/47",
        "imageUrl": "https://ccdn.lezhin.com/v2/comics/5551016703033344/episodes/6153093142085632/images/cover.jpg",
        "publicationDate": "19.12.21"
    },
    {
        "title": "128일 후",
        "url": "https://www.lezhin.com/ko/comic/sleepingman/46",
        "imageUrl": "https://ccdn.lezhin.com/v2/comics/5551016703033344/episodes/5100667324465152/images/cover.jpg",
        "publicationDate": "19.12.14"
    },
    {
        "title": "64일 후",
        "url": "https://www.lezhin.com/ko/comic/sleepingman/45",
        "imageUrl": "https://ccdn.lezhin.com/v2/comics/5551016703033344/episodes/5926982743097344/images/cover.jpg",
        "publicationDate": "19.12.07"
    },
    {
        "title": "64일 후",
        "url": "https://www.lezhin.com/ko/comic/sleepingman/44",
        "imageUrl": "https://ccdn.lezhin.com/v2/comics/5551016703033344/episodes/6133826010873856/images/cover.jpg",
        "publicationDate": "19.11.30"
    },
    {
        "title": "64일 후",
        "url": "https://www.lezhin.com/ko/comic/sleepingman/43",
        "imageUrl": "https://ccdn.lezhin.com/v2/comics/5551016703033344/episodes/6082548165640192/images/cover.jpg",
        "publicationDate": "19.11.23"
    },
    {
        "title": "64일 후",
        "url": "https://www.lezhin.com/ko/comic/sleepingman/42",
        "imageUrl": "https://ccdn.lezhin.com/v2/comics/5551016703033344/episodes/5606634575233024/images/cover.jpg",
        "publicationDate": "19.11.16"
    },
    {
        "title": "64일 후",
        "url": "https://www.lezhin.com/ko/comic/sleepingman/41",
        "imageUrl": "https://ccdn.lezhin.com/v2/comics/5551016703033344/episodes/4799038178066432/images/cover.jpg",
        "publicationDate": "19.11.09"
    },
    {
        "title": "64일 후 : 2부 1화",
        "url": "https://www.lezhin.com/ko/comic/sleepingman/40",
        "imageUrl": "https://ccdn.lezhin.com/v2/comics/5551016703033344/episodes/6245352938012672/images/cover.jpg",
        "publicationDate": "19.11.02"
    },
    {
        "title": "1부 후기",
        "url": "https://www.lezhin.com/ko/comic/sleepingman/e1",
        "imageUrl": "https://ccdn.lezhin.com/v2/comics/5551016703033344/episodes/6142028486148096/images/cover.jpg",
        "publicationDate": "19.07.20"
    },
    {
        "title": "64일 후 : 1부 최종화",
        "url": "https://www.lezhin.com/ko/comic/sleepingman/39",
        "imageUrl": "https://ccdn.lezhin.com/v2/comics/5551016703033344/episodes/5344533720989696/images/cover.jpg",
        "publicationDate": "19.10.26"
    },
    {
        "title": "64일 후",
        "url": "https://www.lezhin.com/ko/comic/sleepingman/38",
        "imageUrl": "https://ccdn.lezhin.com/v2/comics/5551016703033344/episodes/5110829635469312/images/cover.jpg",
        "publicationDate": "19.10.19"
    },
    {
        "title": "64일 후",
        "url": "https://www.lezhin.com/ko/comic/sleepingman/37",
        "imageUrl": "https://ccdn.lezhin.com/v2/comics/5551016703033344/episodes/5596331203493888/images/cover.jpg",
        "publicationDate": "19.10.12"
    },
    {
        "title": "64일 후",
        "url": "https://www.lezhin.com/ko/comic/sleepingman/36",
        "imageUrl": "https://ccdn.lezhin.com/v2/comics/5551016703033344/episodes/6183432613658624/images/cover.jpg",
        "publicationDate": "19.09.28"
    },
    {
        "title": "32일 후",
        "url": "https://www.lezhin.com/ko/comic/sleepingman/35",
        "imageUrl": "https://ccdn.lezhin.com/v2/comics/5551016703033344/episodes/4847312416145408/images/cover.jpg",
        "publicationDate": "19.09.21"
    },
    {
        "title": "16일 후",
        "url": "https://www.lezhin.com/ko/comic/sleepingman/34",
        "imageUrl": "https://ccdn.lezhin.com/v2/comics/5551016703033344/episodes/5130944817004544/images/cover.jpg",
        "publicationDate": "19.09.14"
    },
    {
        "title": "16일 후",
        "url": "https://www.lezhin.com/ko/comic/sleepingman/33",
        "imageUrl": "https://ccdn.lezhin.com/v2/comics/5551016703033344/episodes/5055124561854464/images/cover.jpg",
        "publicationDate": "19.09.07"
    },
    {
        "title": "16일 후",
        "url": "https://www.lezhin.com/ko/comic/sleepingman/32",
        "imageUrl": "https://ccdn.lezhin.com/v2/comics/5551016703033344/episodes/5862877366714368/images/cover.jpg",
        "publicationDate": "19.08.31"
    },
    {
        "title": "16일 후",
        "url": "https://www.lezhin.com/ko/comic/sleepingman/31",
        "imageUrl": "https://ccdn.lezhin.com/v2/comics/5551016703033344/episodes/6448829596303360/images/cover.jpg",
        "publicationDate": "19.08.24"
    },
    {
        "title": "8일 후",
        "url": "https://www.lezhin.com/ko/comic/sleepingman/30",
        "imageUrl": "https://ccdn.lezhin.com/v2/comics/5551016703033344/episodes/6577324083249152/images/cover.jpg",
        "publicationDate": "19.08.17"
    },
    {
        "title": "8일 후",
        "url": "https://www.lezhin.com/ko/comic/sleepingman/29",
        "imageUrl": "https://ccdn.lezhin.com/v2/comics/5551016703033344/episodes/5057292501123072/images/cover.jpg",
        "publicationDate": "19.07.13"
    },
    {
        "title": "8일 후",
        "url": "https://www.lezhin.com/ko/comic/sleepingman/28",
        "imageUrl": "https://ccdn.lezhin.com/v2/comics/5551016703033344/episodes/5036543262457856/images/cover.jpg",
        "publicationDate": "19.07.06"
    },
    {
        "title": "8일 후",
        "url": "https://www.lezhin.com/ko/comic/sleepingman/27",
        "imageUrl": "https://ccdn.lezhin.com/v2/comics/5551016703033344/episodes/6538134728081408/images/cover.jpg",
        "publicationDate": "19.06.29"
    },
    {
        "title": "8일 후",
        "url": "https://www.lezhin.com/ko/comic/sleepingman/26",
        "imageUrl": "https://ccdn.lezhin.com/v2/comics/5551016703033344/episodes/6084171633393664/images/cover.jpg",
        "publicationDate": "19.06.22"
    },
    {
        "title": "8일 후",
        "url": "https://www.lezhin.com/ko/comic/sleepingman/25",
        "imageUrl": "https://ccdn.lezhin.com/v2/comics/5551016703033344/episodes/6714135701487616/images/cover.jpg",
        "publicationDate": "19.06.15"
    },
    {
        "title": "8일 후",
        "url": "https://www.lezhin.com/ko/comic/sleepingman/24",
        "imageUrl": "https://ccdn.lezhin.com/v2/comics/5551016703033344/episodes/5766182849609728/images/cover.jpg",
        "publicationDate": "19.06.08"
    },
    {
        "title": "8일 후",
        "url": "https://www.lezhin.com/ko/comic/sleepingman/23",
        "imageUrl": "https://ccdn.lezhin.com/v2/comics/5551016703033344/episodes/5560929789280256/images/cover.jpg",
        "publicationDate": "19.05.25"
    },
    {
        "title": "8일 후",
        "url": "https://www.lezhin.com/ko/comic/sleepingman/22",
        "imageUrl": "https://ccdn.lezhin.com/v2/comics/5551016703033344/episodes/4718385587159040/images/cover.jpg",
        "publicationDate": "19.05.18"
    },
    {
        "title": "4일 후",
        "url": "https://www.lezhin.com/ko/comic/sleepingman/21",
        "imageUrl": "https://ccdn.lezhin.com/v2/comics/5551016703033344/episodes/6295840160612352/images/cover.jpg",
        "publicationDate": "19.05.11"
    },
    {
        "title": "4일 후",
        "url": "https://www.lezhin.com/ko/comic/sleepingman/20",
        "imageUrl": "https://ccdn.lezhin.com/v2/comics/5551016703033344/episodes/5546537452437504/images/cover.jpg",
        "publicationDate": "19.04.27"
    },
    {
        "title": "4일 후",
        "url": "https://www.lezhin.com/ko/comic/sleepingman/19",
        "imageUrl": "https://ccdn.lezhin.com/v2/comics/5551016703033344/episodes/4773411845177344/images/cover.jpg",
        "publicationDate": "19.04.20"
    },
    {
        "title": "4일 후",
        "url": "https://www.lezhin.com/ko/comic/sleepingman/18",
        "imageUrl": "https://ccdn.lezhin.com/v2/comics/5551016703033344/episodes/4694902376366080/images/cover.jpg",
        "publicationDate": "19.04.13"
    },
    {
        "title": "4일 후",
        "url": "https://www.lezhin.com/ko/comic/sleepingman/17",
        "imageUrl": "https://ccdn.lezhin.com/v2/comics/5551016703033344/episodes/5473827557867520/images/cover.jpg",
        "publicationDate": "19.04.06"
    },
    {
        "title": "2일 후",
        "url": "https://www.lezhin.com/ko/comic/sleepingman/16",
        "imageUrl": "https://ccdn.lezhin.com/v2/comics/5551016703033344/episodes/5275341392576512/images/cover.jpg",
        "publicationDate": "19.03.30"
    },
    {
        "title": "2일 후",
        "url": "https://www.lezhin.com/ko/comic/sleepingman/15",
        "imageUrl": "https://ccdn.lezhin.com/v2/comics/5551016703033344/episodes/5414859772919808/images/cover.jpg",
        "publicationDate": "19.03.23"
    },
    {
        "title": "2일 후",
        "url": "https://www.lezhin.com/ko/comic/sleepingman/14",
        "imageUrl": "https://ccdn.lezhin.com/v2/comics/5551016703033344/episodes/6414046354341888/images/cover.jpg",
        "publicationDate": "19.03.16"
    },
    {
        "title": "2일 후",
        "url": "https://www.lezhin.com/ko/comic/sleepingman/13",
        "imageUrl": "https://ccdn.lezhin.com/v2/comics/5551016703033344/episodes/6330274786443264/images/cover.jpg",
        "publicationDate": "19.03.09"
    },
    {
        "title": "2일 후",
        "url": "https://www.lezhin.com/ko/comic/sleepingman/12",
        "imageUrl": "https://ccdn.lezhin.com/v2/comics/5551016703033344/episodes/5712984789352448/images/cover.jpg",
        "publicationDate": "19.03.02"
    },
    {
        "title": "2일 후",
        "url": "https://www.lezhin.com/ko/comic/sleepingman/11",
        "imageUrl": "https://ccdn.lezhin.com/v2/comics/5551016703033344/episodes/6412241024450560/images/cover.jpg",
        "publicationDate": "19.02.23"
    },
    {
        "title": "2일 후",
        "url": "https://www.lezhin.com/ko/comic/sleepingman/10",
        "imageUrl": "https://ccdn.lezhin.com/v2/comics/5551016703033344/episodes/6477157328617472/images/cover.jpg",
        "publicationDate": "19.02.16"
    },
    {
        "title": "2일 후",
        "url": "https://www.lezhin.com/ko/comic/sleepingman/9",
        "imageUrl": "https://ccdn.lezhin.com/v2/comics/5551016703033344/episodes/6585713545576448/images/cover.jpg",
        "publicationDate": "19.02.02"
    },
    {
        "title": "24시간 후",
        "url": "https://www.lezhin.com/ko/comic/sleepingman/8",
        "imageUrl": "https://ccdn.lezhin.com/v2/comics/5551016703033344/episodes/4841349844697088/images/cover.jpg",
        "publicationDate": "19.01.26"
    },
    {
        "title": "24시간 후",
        "url": "https://www.lezhin.com/ko/comic/sleepingman/7",
        "imageUrl": "https://ccdn.lezhin.com/v2/comics/5551016703033344/episodes/5398922209656832/images/cover.jpg",
        "publicationDate": "19.01.19"
    },
    {
        "title": "24시간 후",
        "url": "https://www.lezhin.com/ko/comic/sleepingman/6",
        "imageUrl": "https://ccdn.lezhin.com/v2/comics/5551016703033344/episodes/4980240610361344/images/cover.jpg",
        "publicationDate": "19.01.12"
    },
    {
        "title": "12시간 후",
        "url": "https://www.lezhin.com/ko/comic/sleepingman/5",
        "imageUrl": "https://ccdn.lezhin.com/v2/comics/5551016703033344/episodes/5869875226083328/images/cover.jpg",
        "publicationDate": "19.01.05"
    },
    {
        "title": "12시간 후",
        "url": "https://www.lezhin.com/ko/comic/sleepingman/4",
        "imageUrl": "https://ccdn.lezhin.com/v2/comics/5551016703033344/episodes/5077103699165184/images/cover.jpg",
        "publicationDate": "18.12.29"
    },
    {
        "title": "6시간 후",
        "url": "https://www.lezhin.com/ko/comic/sleepingman/3",
        "imageUrl": "https://ccdn.lezhin.com/v2/comics/5551016703033344/episodes/5876026906902528/images/cover.jpg",
        "publicationDate": "18.12.22"
    },
    {
        "title": "6시간 후",
        "url": "https://www.lezhin.com/ko/comic/sleepingman/2",
        "imageUrl": "https://ccdn.lezhin.com/v2/comics/5551016703033344/episodes/5612101556633600/images/cover.jpg",
        "publicationDate": "18.12.15"
    },
    {
        "title": "3시간 후",
        "url": "https://www.lezhin.com/ko/comic/sleepingman/1",
        "imageUrl": "https://ccdn.lezhin.com/v2/comics/5551016703033344/episodes/4743382324346880/images/cover.jpg",
        "publicationDate": "18.12.08"
    },
    {
        "title": "프롤로그",
        "url": "https://www.lezhin.com/ko/comic/sleepingman/p1",
        "imageUrl": "https://ccdn.lezhin.com/v2/comics/5551016703033344/episodes/5851000098914304/images/cover.jpg",
        "publicationDate": "18.12.08"
    }
]