[
    {
        "title": "309. 최종전(3)",
        "url": "https://comic.naver.com/webtoon/detail?titleId=702608&no=309&week=tue",
        "imageUrl": "https://image-comic.pstatic.net/webtoon/702608/309/thumbnail_202x120_07e71317-a06f-4f0e-9223-68cef570807c.jpg",
        "publicationDate": "23.11.20"
    },
    {
        "title": "308. 최종전(2)",
        "url": "https://comic.naver.com/webtoon/detail?titleId=702608&no=308&week=tue",
        "imageUrl": "https://image-comic.pstatic.net/webtoon/702608/308/thumbnail_202x120_e7355c3e-3214-43f1-ac41-400478868bed.jpg",
        "publicationDate": "23.11.13"
    },
    {
        "title": "307. 최종전(1)",
        "url": "https://comic.naver.com/webtoon/detail?titleId=702608&no=307&week=tue",
        "imageUrl": "https://image-comic.pstatic.net/webtoon/702608/307/thumbnail_202x120_f22fced4-f8f6-4c4d-b639-beffe87d9ec7.jpg",
        "publicationDate": "23.11.06"
    },
    {
        "title": "306. 끝의 끝까지",
        "url": "https://comic.naver.com/webtoon/detail?titleId=702608&no=306&week=tue",
        "imageUrl": "https://image-comic.pstatic.net/webtoon/702608/306/thumbnail_202x120_a4ba7530-6049-4058-b54c-c1a7e42d2f0b.jpg",
        "publicationDate": "23.10.30"
    },
    {
        "title": "305. 싸이코패스",
        "url": "https://comic.naver.com/webtoon/detail?titleId=702608&no=305&week=tue",
        "imageUrl": "https://image-comic.pstatic.net/webtoon/702608/305/thumbnail_202x120_8e16e7fe-d192-4583-8a99-1f379b3e12f2.jpg",
        "publicationDate": "23.10.23"
    },
    {
        "title": "304. 시간이 갈수록 악화되는것",
        "url": "https://comic.naver.com/webtoon/detail?titleId=702608&no=304&week=tue",
        "imageUrl": "https://image-comic.pstatic.net/webtoon/702608/304/thumbnail_202x120_67505c56-be12-4ff3-bb48-565175663cf3.jpg",
        "publicationDate": "23.10.16"
    },
    {
        "title": "303. 시간이 흐른다고",
        "url": "https://comic.naver.com/webtoon/detail?titleId=702608&no=303&week=tue",
        "imageUrl": "https://image-comic.pstatic.net/webtoon/702608/303/thumbnail_202x120_b5286967-be17-4835-a07c-4cf07838bd9e.jpg",
        "publicationDate": "23.10.09"
    },
    {
        "title": "302. 흉터",
        "url": "https://comic.naver.com/webtoon/detail?titleId=702608&no=302&week=tue",
        "imageUrl": "https://image-comic.pstatic.net/webtoon/702608/302/thumbnail_202x120_31bdb9e7-3cf3-4380-a76b-15392140a23b.jpg",
        "publicationDate": "23.10.02"
    },
    {
        "title": "301. 세상 좁다",
        "url": "https://comic.naver.com/webtoon/detail?titleId=702608&no=301&week=tue",
        "imageUrl": "https://image-comic.pstatic.net/webtoon/702608/301/thumbnail_202x120_d3d133ca-91a0-4b5a-888c-d05949fe101f.jpg",
        "publicationDate": "23.09.25"
    },
    {
        "title": "300. 안녕 나의 + 300화 특별편",
        "url": "https://comic.naver.com/webtoon/detail?titleId=702608&no=300&week=tue",
        "imageUrl": "https://image-comic.pstatic.net/webtoon/702608/300/thumbnail_202x120_7e8cd1e8-bc10-41be-bd78-2fae3b2053d3.jpg",
        "publicationDate": "23.09.18"
    },
    {
        "title": "299. 친구와 원수 사이",
        "url": "https://comic.naver.com/webtoon/detail?titleId=702608&no=299&week=tue",
        "imageUrl": "https://image-comic.pstatic.net/webtoon/702608/299/thumbnail_202x120_a546621c-99fa-49cf-a101-cc31dfd4ee1b.jpg",
        "publicationDate": "23.09.11"
    },
    {
        "title": "298. 정말 안녕 내 첫사랑",
        "url": "https://comic.naver.com/webtoon/detail?titleId=702608&no=298&week=tue",
        "imageUrl": "https://image-comic.pstatic.net/webtoon/702608/298/thumbnail_202x120_d758de99-43cc-4e69-803e-6f04b505ea2d.jpg",
        "publicationDate": "23.09.04"
    },
    {
        "title": "297. 안녕 내 첫사랑",
        "url": "https://comic.naver.com/webtoon/detail?titleId=702608&no=297&week=tue",
        "imageUrl": "https://image-comic.pstatic.net/webtoon/702608/297/thumbnail_202x120_f3144c67-76f6-48b1-b3ac-348015770569.jpg",
        "publicationDate": "23.08.28"
    },
    {
        "title": "296. 연인에게 가장 무서운것",
        "url": "https://comic.naver.com/webtoon/detail?titleId=702608&no=296&week=tue",
        "imageUrl": "https://image-comic.pstatic.net/webtoon/702608/296/thumbnail_202x120_d4d2e205-d5b9-417e-be81-0f08a81b6336.jpg",
        "publicationDate": "23.08.14"
    },
    {
        "title": "295. 첫사랑은 한번이다",
        "url": "https://comic.naver.com/webtoon/detail?titleId=702608&no=295&week=tue",
        "imageUrl": "https://image-comic.pstatic.net/webtoon/702608/295/thumbnail_202x120_a4b650eb-3054-4092-950f-f78b4aba4601.jpg",
        "publicationDate": "23.08.07"
    },
    {
        "title": "294. 홀로서기3",
        "url": "https://comic.naver.com/webtoon/detail?titleId=702608&no=294&week=tue",
        "imageUrl": "https://image-comic.pstatic.net/webtoon/702608/294/thumbnail_202x120_540fa0dc-c1ec-4ed8-aff1-2d394a98e0be.jpg",
        "publicationDate": "23.07.31"
    },
    {
        "title": "293. 홀로서기2",
        "url": "https://comic.naver.com/webtoon/detail?titleId=702608&no=293&week=tue",
        "imageUrl": "https://image-comic.pstatic.net/webtoon/702608/293/thumbnail_202x120_1d08568a-3fe1-452f-a65d-5b6c46b1670a.jpg",
        "publicationDate": "23.07.24"
    },
    {
        "title": "292. 홀로서기",
        "url": "https://comic.naver.com/webtoon/detail?titleId=702608&no=292&week=tue",
        "imageUrl": "https://image-comic.pstatic.net/webtoon/702608/292/thumbnail_202x120_64e60ac7-26e4-4bc8-ab0c-415bf476cd10.jpg",
        "publicationDate": "23.07.17"
    },
    {
        "title": "291. 그대가 없는 세상",
        "url": "https://comic.naver.com/webtoon/detail?titleId=702608&no=291&week=tue",
        "imageUrl": "https://image-comic.pstatic.net/webtoon/702608/291/thumbnail_202x120_34ece9aa-0a1d-4566-8d53-59a4e53782ee.jpg",
        "publicationDate": "23.07.10"
    },
    {
        "title": "290. we're floating in space",
        "url": "https://comic.naver.com/webtoon/detail?titleId=702608&no=290&week=tue",
        "imageUrl": "https://image-comic.pstatic.net/webtoon/702608/290/thumbnail_202x120_1d968d1e-fdd5-4cf5-a318-cf7f4bb8ad71.jpg",
        "publicationDate": "23.07.03"
    },
    {
        "title": "289. 모두에게",
        "url": "https://comic.naver.com/webtoon/detail?titleId=702608&no=289&week=tue",
        "imageUrl": "https://image-comic.pstatic.net/webtoon/702608/289/thumbnail_202x120_4ae59238-051c-4de1-8c84-a492bb1d9438.jpg",
        "publicationDate": "23.06.26"
    },
    {
        "title": "288. 자기불신의 아이러니",
        "url": "https://comic.naver.com/webtoon/detail?titleId=702608&no=288&week=tue",
        "imageUrl": "https://image-comic.pstatic.net/webtoon/702608/288/thumbnail_202x120_f3bca00d-d6e6-48a9-bb95-4dae14833e4d.jpg",
        "publicationDate": "23.06.19"
    },
    {
        "title": "287. 4의 남자",
        "url": "https://comic.naver.com/webtoon/detail?titleId=702608&no=287&week=tue",
        "imageUrl": "https://image-comic.pstatic.net/webtoon/702608/287/thumbnail_202x120_5a0af557-05f6-4f5d-8159-a63e9f1f4aa9.jpg",
        "publicationDate": "23.06.12"
    },
    {
        "title": "286. 사랑방식",
        "url": "https://comic.naver.com/webtoon/detail?titleId=702608&no=286&week=tue",
        "imageUrl": "https://image-comic.pstatic.net/webtoon/702608/286/thumbnail_202x120_07ce106f-0f3b-43a1-8983-59bba87a0934.jpg",
        "publicationDate": "23.05.29"
    },
    {
        "title": "285. 진실게임",
        "url": "https://comic.naver.com/webtoon/detail?titleId=702608&no=285&week=tue",
        "imageUrl": "https://image-comic.pstatic.net/webtoon/702608/285/thumbnail_202x120_233ece8a-86ac-4c94-bf19-9e91fc53a049.jpg",
        "publicationDate": "23.05.22"
    },
    {
        "title": "284. 비밀친구",
        "url": "https://comic.naver.com/webtoon/detail?titleId=702608&no=284&week=tue",
        "imageUrl": "https://image-comic.pstatic.net/webtoon/702608/284/thumbnail_202x120_407a0a15-2074-4e6c-9320-300979fc4ecd.jpg",
        "publicationDate": "23.05.15"
    },
    {
        "title": "283. 애매하게",
        "url": "https://comic.naver.com/webtoon/detail?titleId=702608&no=283&week=tue",
        "imageUrl": "https://image-comic.pstatic.net/webtoon/702608/283/thumbnail_202x120_a448b7ac-c13f-4069-82c4-2066c0dac036.jpg",
        "publicationDate": "23.05.08"
    },
    {
        "title": "282. 이제는 우리가",
        "url": "https://comic.naver.com/webtoon/detail?titleId=702608&no=282&week=tue",
        "imageUrl": "https://image-comic.pstatic.net/webtoon/702608/282/thumbnail_202x120_1009ef5f-839d-4c34-8773-0588cd57e3d8.jpg",
        "publicationDate": "23.05.01"
    },
    {
        "title": "281. 왜 그렇게까지 해",
        "url": "https://comic.naver.com/webtoon/detail?titleId=702608&no=281&week=tue",
        "imageUrl": "https://image-comic.pstatic.net/webtoon/702608/281/thumbnail_202x120_4893c3a3-d8d5-4975-9e03-aa9079a84617.jpg",
        "publicationDate": "23.04.24"
    },
    {
        "title": "280. 눈빛",
        "url": "https://comic.naver.com/webtoon/detail?titleId=702608&no=280&week=tue",
        "imageUrl": "https://image-comic.pstatic.net/webtoon/702608/280/thumbnail_202x120_7bd3c11f-dd94-4c1e-8c22-31034ba901ae.jpg",
        "publicationDate": "23.04.17"
    },
    {
        "title": "279. 폭풍처럼",
        "url": "https://comic.naver.com/webtoon/detail?titleId=702608&no=279&week=tue",
        "imageUrl": "https://image-comic.pstatic.net/webtoon/702608/279/thumbnail_202x120_9803323c-332d-4aa3-8c14-0bb058733253.jpg",
        "publicationDate": "23.04.10"
    },
    {
        "title": "278. 마지막 선택지",
        "url": "https://comic.naver.com/webtoon/detail?titleId=702608&no=278&week=tue",
        "imageUrl": "https://image-comic.pstatic.net/webtoon/702608/278/thumbnail_202x120_b6bf2e41-f205-40fc-9118-4a896caf65c5.jpg",
        "publicationDate": "23.04.03"
    },
    {
        "title": "277. 바보들",
        "url": "https://comic.naver.com/webtoon/detail?titleId=702608&no=277&week=tue",
        "imageUrl": "https://image-comic.pstatic.net/webtoon/702608/277/thumbnail_202x120_c12b8878-793d-45b0-a0a6-b54b12b5663e.jpg",
        "publicationDate": "23.03.27"
    },
    {
        "title": "276. 꿈",
        "url": "https://comic.naver.com/webtoon/detail?titleId=702608&no=276&week=tue",
        "imageUrl": "https://image-comic.pstatic.net/webtoon/702608/276/thumbnail_202x120_c17837f5-979e-4e86-bbc3-2091632ac196.jpg",
        "publicationDate": "23.03.20"
    },
    {
        "title": "275. 이것도 능력",
        "url": "https://comic.naver.com/webtoon/detail?titleId=702608&no=275&week=tue",
        "imageUrl": "https://image-comic.pstatic.net/webtoon/702608/275/thumbnail_202x120_86a04d4e-dbc4-48d1-9f08-65d8c2b6a7eb.jpg",
        "publicationDate": "23.03.13"
    },
    {
        "title": "274. 마음 바꾸기",
        "url": "https://comic.naver.com/webtoon/detail?titleId=702608&no=274&week=tue",
        "imageUrl": "https://image-comic.pstatic.net/webtoon/702608/274/thumbnail_202x120_960d3914-17ae-46a4-9f58-9fd53e34c1c7.jpg",
        "publicationDate": "23.03.06"
    },
    {
        "title": "273. 전하고 싶은 말",
        "url": "https://comic.naver.com/webtoon/detail?titleId=702608&no=273&week=tue",
        "imageUrl": "https://image-comic.pstatic.net/webtoon/702608/273/thumbnail_202x120_5cbe477a-e8a7-42f5-81b1-faec550bc2f7.jpg",
        "publicationDate": "23.02.27"
    },
    {
        "title": "272. 패배자가 살아가는 법",
        "url": "https://comic.naver.com/webtoon/detail?titleId=702608&no=272&week=tue",
        "imageUrl": "https://image-comic.pstatic.net/webtoon/702608/272/thumbnail_202x120_a7bddc00-0b84-4f72-aa77-e00491d8237e.jpg",
        "publicationDate": "23.02.20"
    },
    {
        "title": "271. 시간과 목적",
        "url": "https://comic.naver.com/webtoon/detail?titleId=702608&no=271&week=tue",
        "imageUrl": "https://image-comic.pstatic.net/webtoon/702608/271/thumbnail_202x120_ec2f1d0a-4e4e-42dd-a847-ae5d788cc0a5.jpg",
        "publicationDate": "23.02.13"
    },
    {
        "title": "270. 선택과 자유",
        "url": "https://comic.naver.com/webtoon/detail?titleId=702608&no=270&week=tue",
        "imageUrl": "https://image-comic.pstatic.net/webtoon/702608/270/thumbnail_202x120_13a0cbef-5dab-4db2-b0e2-c61d06fe9c01.jpg",
        "publicationDate": "23.02.06"
    },
    {
        "title": "269. 시간이 알려준다",
        "url": "https://comic.naver.com/webtoon/detail?titleId=702608&no=269&week=tue",
        "imageUrl": "https://image-comic.pstatic.net/webtoon/702608/269/thumbnail_202x120_66d9cb59-0604-4a43-8474-7e5d2d83beca.jpg",
        "publicationDate": "23.01.30"
    },
    {
        "title": "268. 하늘을 보면서",
        "url": "https://comic.naver.com/webtoon/detail?titleId=702608&no=268&week=tue",
        "imageUrl": "https://image-comic.pstatic.net/webtoon/702608/268/thumbnail_202x120_13b36221-214d-4748-99fc-f4e77e3e94c7.jpg",
        "publicationDate": "23.01.23"
    },
    {
        "title": "267. 비밀없는사이",
        "url": "https://comic.naver.com/webtoon/detail?titleId=702608&no=267&week=tue",
        "imageUrl": "https://image-comic.pstatic.net/webtoon/702608/267/thumbnail_202x120_f64adb72-e965-4bdf-89ef-2485a2a6d171.jpg",
        "publicationDate": "23.01.16"
    },
    {
        "title": "266. 한명만 만나야 한다면",
        "url": "https://comic.naver.com/webtoon/detail?titleId=702608&no=266&week=tue",
        "imageUrl": "https://image-comic.pstatic.net/webtoon/702608/266/thumbnail_202x120_9bfb14c1-6c75-47a9-bc16-e5285fd74edb.jpg",
        "publicationDate": "23.01.09"
    },
    {
        "title": "265. 지킬 건 지키자",
        "url": "https://comic.naver.com/webtoon/detail?titleId=702608&no=265&week=tue",
        "imageUrl": "https://image-comic.pstatic.net/webtoon/702608/265/thumbnail_202x120_56ae2279-e7ee-49fd-8962-ed3a6543e294.jpg",
        "publicationDate": "23.01.02"
    },
    {
        "title": "264. 사랑과 합리화",
        "url": "https://comic.naver.com/webtoon/detail?titleId=702608&no=264&week=tue",
        "imageUrl": "https://image-comic.pstatic.net/webtoon/702608/264/thumbnail_202x120_0b5e55a6-2f30-4e68-bff5-7da606bbd4bf.jpg",
        "publicationDate": "22.12.26"
    },
    {
        "title": "263. Redpill",
        "url": "https://comic.naver.com/webtoon/detail?titleId=702608&no=263&week=tue",
        "imageUrl": "https://image-comic.pstatic.net/webtoon/702608/263/thumbnail_202x120_98eeb717-ec0a-4cf6-b5c9-27170ca7d15f.jpg",
        "publicationDate": "22.12.19"
    },
    {
        "title": "262. 자기발전",
        "url": "https://comic.naver.com/webtoon/detail?titleId=702608&no=262&week=tue",
        "imageUrl": "https://image-comic.pstatic.net/webtoon/702608/262/thumbnail_202x120_cd90134c-59c3-4fb5-a7b6-af4d0e2fe66b.jpg",
        "publicationDate": "22.12.12"
    },
    {
        "title": "261. 불공평",
        "url": "https://comic.naver.com/webtoon/detail?titleId=702608&no=261&week=tue",
        "imageUrl": "https://image-comic.pstatic.net/webtoon/702608/261/thumbnail_202x120_7a5bf272-7fda-4693-a27a-25ae79406bdd.jpg",
        "publicationDate": "22.12.05"
    },
    {
        "title": "260. 염세주의",
        "url": "https://comic.naver.com/webtoon/detail?titleId=702608&no=260&week=tue",
        "imageUrl": "https://image-comic.pstatic.net/webtoon/702608/260/thumbnail_202x120_db12b12d-f2d1-44f0-adc7-b8c66ffbad65.jpg",
        "publicationDate": "22.11.28"
    },
    {
        "title": "259. 감정의 무게",
        "url": "https://comic.naver.com/webtoon/detail?titleId=702608&no=259&week=tue",
        "imageUrl": "https://image-comic.pstatic.net/webtoon/702608/259/thumbnail_202x120_027c13ff-02ac-45b4-9ab5-3584342fe854.jpg",
        "publicationDate": "22.11.21"
    },
    {
        "title": "258. 필요해",
        "url": "https://comic.naver.com/webtoon/detail?titleId=702608&no=258&week=tue",
        "imageUrl": "https://image-comic.pstatic.net/webtoon/702608/258/thumbnail_202x120_da4c7f69-01c6-4677-88f9-530f79f16950.jpg",
        "publicationDate": "22.11.14"
    },
    {
        "title": "257. 경고",
        "url": "https://comic.naver.com/webtoon/detail?titleId=702608&no=257&week=tue",
        "imageUrl": "https://image-comic.pstatic.net/webtoon/702608/257/thumbnail_202x120_5310b901-2533-4e57-9be6-1f80f8bc6287.jpg",
        "publicationDate": "22.11.07"
    },
    {
        "title": "256. 말하지 않아도",
        "url": "https://comic.naver.com/webtoon/detail?titleId=702608&no=256&week=tue",
        "imageUrl": "https://image-comic.pstatic.net/webtoon/702608/256/thumbnail_202x120_c008695f-5f85-4a5c-a03a-23a252a54c36.jpg",
        "publicationDate": "22.10.31"
    },
    {
        "title": "255. 나의 청춘",
        "url": "https://comic.naver.com/webtoon/detail?titleId=702608&no=255&week=tue",
        "imageUrl": "https://image-comic.pstatic.net/webtoon/702608/255/thumbnail_202x120_434734bf-cb47-450a-b2ac-f15aaee84822.jpg",
        "publicationDate": "22.10.24"
    },
    {
        "title": "254. 개장수",
        "url": "https://comic.naver.com/webtoon/detail?titleId=702608&no=254&week=tue",
        "imageUrl": "https://image-comic.pstatic.net/webtoon/702608/254/thumbnail_202x120_d42e8c03-b14d-4615-a80a-8128dab88d91.jpg",
        "publicationDate": "22.10.17"
    },
    {
        "title": "253. 기분",
        "url": "https://comic.naver.com/webtoon/detail?titleId=702608&no=253&week=tue",
        "imageUrl": "https://image-comic.pstatic.net/webtoon/702608/253/thumbnail_202x120_4b702582-badd-447d-aae4-894b3f3fc2ad.jpg",
        "publicationDate": "22.10.10"
    },
    {
        "title": "252. 은밀하게 거대하게",
        "url": "https://comic.naver.com/webtoon/detail?titleId=702608&no=252&week=tue",
        "imageUrl": "https://image-comic.pstatic.net/webtoon/702608/252/thumbnail_202x120_b874bc5f-aa27-4be6-9c9f-a89db588e240.jpg",
        "publicationDate": "22.10.03"
    },
    {
        "title": "251. 달빛의 이정표",
        "url": "https://comic.naver.com/webtoon/detail?titleId=702608&no=251&week=tue",
        "imageUrl": "https://image-comic.pstatic.net/webtoon/702608/251/thumbnail_202x120_172dc972-a88f-4b5d-bcd4-ae4413244f10.jpg",
        "publicationDate": "22.09.26"
    },
    {
        "title": "250. 악인",
        "url": "https://comic.naver.com/webtoon/detail?titleId=702608&no=250&week=tue",
        "imageUrl": "https://image-comic.pstatic.net/webtoon/702608/250/thumbnail_202x120_be14bc5a-ae7a-4275-a937-0a14f15f5c90.jpg",
        "publicationDate": "22.09.19"
    },
    {
        "title": "249. 나비효과",
        "url": "https://comic.naver.com/webtoon/detail?titleId=702608&no=249&week=tue",
        "imageUrl": "https://image-comic.pstatic.net/webtoon/702608/249/thumbnail_202x120_90d76c7c-530b-41a9-b75a-f7dd48bd9c4c.jpg",
        "publicationDate": "22.09.12"
    },
    {
        "title": "248. 그럼에도 불구하고",
        "url": "https://comic.naver.com/webtoon/detail?titleId=702608&no=248&week=tue",
        "imageUrl": "https://image-comic.pstatic.net/webtoon/702608/248/thumbnail_202x120_c8f1c51b-ea2c-4f27-90b6-6447ef1ed577.jpg",
        "publicationDate": "22.09.05"
    },
    {
        "title": "247. 최준우의 미로",
        "url": "https://comic.naver.com/webtoon/detail?titleId=702608&no=247&week=tue",
        "imageUrl": "https://image-comic.pstatic.net/webtoon/702608/247/thumbnail_202x120_039cb042-a8c4-4440-bb55-97b16942e3f5.jpg",
        "publicationDate": "22.08.29"
    },
    {
        "title": "246. 박하민의 미로",
        "url": "https://comic.naver.com/webtoon/detail?titleId=702608&no=246&week=tue",
        "imageUrl": "https://image-comic.pstatic.net/webtoon/702608/246/thumbnail_202x120_86c41602-c340-496a-a7d0-dfb99817f372.jpg",
        "publicationDate": "22.08.22"
    },
    {
        "title": "245. 해야할 이야기",
        "url": "https://comic.naver.com/webtoon/detail?titleId=702608&no=245&week=tue",
        "imageUrl": "https://image-comic.pstatic.net/webtoon/702608/245/thumbnail_202x120_8d9d380f-b84e-474d-a0a1-b49a2fff9313.jpg",
        "publicationDate": "22.08.15"
    },
    {
        "title": "244. 안티테제",
        "url": "https://comic.naver.com/webtoon/detail?titleId=702608&no=244&week=tue",
        "imageUrl": "https://image-comic.pstatic.net/webtoon/702608/244/thumbnail_202x120_9d4f1764-87cc-4dca-b31b-d62d99d695a2.jpg",
        "publicationDate": "22.08.08"
    },
    {
        "title": "243. 상처는 사람을 바꾼다",
        "url": "https://comic.naver.com/webtoon/detail?titleId=702608&no=243&week=tue",
        "imageUrl": "https://image-comic.pstatic.net/webtoon/702608/243/thumbnail_202x120_8e62ab06-f662-42e0-8ded-9026ca87b8a0.jpg",
        "publicationDate": "22.08.01"
    },
    {
        "title": "242. 수학여행",
        "url": "https://comic.naver.com/webtoon/detail?titleId=702608&no=242&week=tue",
        "imageUrl": "https://image-comic.pstatic.net/webtoon/702608/242/thumbnail_202x120_8a14dba8-c3c2-409e-9f6a-545c59ea3720.jpg",
        "publicationDate": "22.07.18"
    },
    {
        "title": "241. 놈놈놈",
        "url": "https://comic.naver.com/webtoon/detail?titleId=702608&no=241&week=tue",
        "imageUrl": "https://image-comic.pstatic.net/webtoon/702608/241/thumbnail_202x120_448885a3-85d9-4816-abe5-7f0366000ef2.jpg",
        "publicationDate": "22.07.11"
    },
    {
        "title": "240. 권리",
        "url": "https://comic.naver.com/webtoon/detail?titleId=702608&no=240&week=tue",
        "imageUrl": "https://image-comic.pstatic.net/webtoon/702608/240/thumbnail_202x120_13f4be9a-6158-4644-b217-faa7a316e1f9.jpg",
        "publicationDate": "22.07.04"
    },
    {
        "title": "239. 무슨일이 일어나고 있는 거야",
        "url": "https://comic.naver.com/webtoon/detail?titleId=702608&no=239&week=tue",
        "imageUrl": "https://image-comic.pstatic.net/webtoon/702608/239/thumbnail_202x120_01b329b3-9770-4384-beba-a2e48831ce24.jpg",
        "publicationDate": "22.06.27"
    },
    {
        "title": "238. 일편단심",
        "url": "https://comic.naver.com/webtoon/detail?titleId=702608&no=238&week=tue",
        "imageUrl": "https://image-comic.pstatic.net/webtoon/702608/238/thumbnail_202x120_c02df520-11d1-4182-b991-6986de5e717a.jpg",
        "publicationDate": "22.06.20"
    },
    {
        "title": "237. 끝과 시작",
        "url": "https://comic.naver.com/webtoon/detail?titleId=702608&no=237&week=tue",
        "imageUrl": "https://image-comic.pstatic.net/webtoon/702608/237/thumbnail_202x120_f3b26a58-4e12-45bf-8173-2ca1185d1bd7.jpg",
        "publicationDate": "22.06.13"
    },
    {
        "title": "236. 너의 적",
        "url": "https://comic.naver.com/webtoon/detail?titleId=702608&no=236&week=tue",
        "imageUrl": "https://image-comic.pstatic.net/webtoon/702608/236/thumbnail_202x120_6704eb33-d559-4005-80ba-ad408ce339c7.jpg",
        "publicationDate": "22.06.06"
    },
    {
        "title": "235. 구하지 못한 것",
        "url": "https://comic.naver.com/webtoon/detail?titleId=702608&no=235&week=tue",
        "imageUrl": "https://image-comic.pstatic.net/webtoon/702608/235/thumbnail_202x120_3a56c622-0b6a-46c0-bcf8-6214ddc0c1d2.jpg",
        "publicationDate": "22.05.30"
    },
    {
        "title": "234. 돌아보지 못한 사람",
        "url": "https://comic.naver.com/webtoon/detail?titleId=702608&no=234&week=tue",
        "imageUrl": "https://image-comic.pstatic.net/webtoon/702608/234/thumbnail_202x120_41ab2b47-91ac-4602-9f6d-08d67250a4ca.jpg",
        "publicationDate": "22.05.23"
    },
    {
        "title": "233. 우리가 함께하는 이유",
        "url": "https://comic.naver.com/webtoon/detail?titleId=702608&no=233&week=tue",
        "imageUrl": "https://image-comic.pstatic.net/webtoon/702608/233/thumbnail_202x120_bb466f0c-8833-4dcc-80bc-99666d459ee1.jpg",
        "publicationDate": "22.05.16"
    },
    {
        "title": "232. 이윤슬",
        "url": "https://comic.naver.com/webtoon/detail?titleId=702608&no=232&week=tue",
        "imageUrl": "https://image-comic.pstatic.net/webtoon/702608/232/thumbnail_202x120_380ff514-0f1f-4e82-864b-c38f8e6497bd.jpg",
        "publicationDate": "22.05.09"
    },
    {
        "title": "231. Go Back",
        "url": "https://comic.naver.com/webtoon/detail?titleId=702608&no=231&week=tue",
        "imageUrl": "https://image-comic.pstatic.net/webtoon/702608/231/thumbnail_202x120_99d6becd-3db5-46e4-a9a6-ba5bfc1eb059.jpg",
        "publicationDate": "22.05.02"
    },
    {
        "title": "230. 톱니바퀴가 반대로 돌면",
        "url": "https://comic.naver.com/webtoon/detail?titleId=702608&no=230&week=tue",
        "imageUrl": "https://image-comic.pstatic.net/webtoon/702608/230/thumbnail_202x120_d90bf3ef-9960-4240-b71f-fe13b95de1d5.jpg",
        "publicationDate": "22.04.25"
    },
    {
        "title": "229. 고장",
        "url": "https://comic.naver.com/webtoon/detail?titleId=702608&no=229&week=tue",
        "imageUrl": "https://image-comic.pstatic.net/webtoon/702608/229/thumbnail_202x120_b05dd18f-7ce8-4322-9132-909ec2ab261b.jpg",
        "publicationDate": "22.04.18"
    },
    {
        "title": "228. 천사와 악마",
        "url": "https://comic.naver.com/webtoon/detail?titleId=702608&no=228&week=tue",
        "imageUrl": "https://image-comic.pstatic.net/webtoon/702608/228/thumbnail_202x120_300c0c98-2a60-4e55-86d5-810e3ede2fee.jpg",
        "publicationDate": "22.04.11"
    },
    {
        "title": "227. 예측할 수 없는 방향으로",
        "url": "https://comic.naver.com/webtoon/detail?titleId=702608&no=227&week=tue",
        "imageUrl": "https://image-comic.pstatic.net/webtoon/702608/227/thumbnail_202x120_21e50574-5e7a-425d-b47d-66f40831c4a4.jpg",
        "publicationDate": "22.04.04"
    },
    {
        "title": "226. 누구를 위해 톱니바퀴는 돌아가는가",
        "url": "https://comic.naver.com/webtoon/detail?titleId=702608&no=226&week=tue",
        "imageUrl": "https://image-comic.pstatic.net/webtoon/702608/226/thumbnail_202x120_42024d40-85a2-47c4-9c93-489ae0c1c11d.jpg",
        "publicationDate": "22.03.28"
    },
    {
        "title": "225. villanus",
        "url": "https://comic.naver.com/webtoon/detail?titleId=702608&no=225&week=tue",
        "imageUrl": "https://image-comic.pstatic.net/webtoon/702608/225/thumbnail_202x120_5bec3981-d140-44f1-943f-8d4843f4ab8b.jpg",
        "publicationDate": "22.03.21"
    },
    {
        "title": "224. 새",
        "url": "https://comic.naver.com/webtoon/detail?titleId=702608&no=224&week=tue",
        "imageUrl": "https://image-comic.pstatic.net/webtoon/702608/224/thumbnail_202x120_785a1867-7212-4adc-9c12-739a3bdd32be.jpg",
        "publicationDate": "22.03.14"
    },
    {
        "title": "223. 불행에 대항하는 법",
        "url": "https://comic.naver.com/webtoon/detail?titleId=702608&no=223&week=tue",
        "imageUrl": "https://image-comic.pstatic.net/webtoon/702608/223/thumbnail_202x120_8a6c6010-dc41-40f3-8419-48b22a5bf99b.jpg",
        "publicationDate": "22.03.07"
    },
    {
        "title": "222. 세상은 너 혼자 사는곳이 아니다.",
        "url": "https://comic.naver.com/webtoon/detail?titleId=702608&no=222&week=tue",
        "imageUrl": "https://image-comic.pstatic.net/webtoon/702608/222/thumbnail_202x120_849f631f-1e35-4aad-816e-917c7a91f819.jpg",
        "publicationDate": "22.02.28"
    },
    {
        "title": "221. 주어진 역할",
        "url": "https://comic.naver.com/webtoon/detail?titleId=702608&no=221&week=tue",
        "imageUrl": "https://image-comic.pstatic.net/webtoon/702608/221/thumbnail_202x120_3d287360-becb-4a51-9af9-2f21d71ab30e.jpg",
        "publicationDate": "22.02.21"
    },
    {
        "title": "220. 거짓말쟁이",
        "url": "https://comic.naver.com/webtoon/detail?titleId=702608&no=220&week=tue",
        "imageUrl": "https://image-comic.pstatic.net/webtoon/702608/220/thumbnail_202x120_83bba26c-d766-4153-8350-57c796932a53.jpg",
        "publicationDate": "22.02.14"
    },
    {
        "title": "219. 재회",
        "url": "https://comic.naver.com/webtoon/detail?titleId=702608&no=219&week=tue",
        "imageUrl": "https://image-comic.pstatic.net/webtoon/702608/219/thumbnail_202x120_f5744a82-829b-4301-bdcd-162132cef5e2.jpg",
        "publicationDate": "22.02.07"
    },
    {
        "title": "218. 이유가 필요해?",
        "url": "https://comic.naver.com/webtoon/detail?titleId=702608&no=218&week=tue",
        "imageUrl": "https://image-comic.pstatic.net/webtoon/702608/218/thumbnail_202x120_2bf482d1-93f8-44cf-bb7f-0dfabef1b294.jpg",
        "publicationDate": "22.01.31"
    },
    {
        "title": "217. 감동",
        "url": "https://comic.naver.com/webtoon/detail?titleId=702608&no=217&week=tue",
        "imageUrl": "https://image-comic.pstatic.net/webtoon/702608/217/thumbnail_202x120_5523bded-4219-4768-9e52-8ecca419895c.jpg",
        "publicationDate": "22.01.17"
    },
    {
        "title": "216. 각오",
        "url": "https://comic.naver.com/webtoon/detail?titleId=702608&no=216&week=tue",
        "imageUrl": "https://image-comic.pstatic.net/webtoon/702608/216/thumbnail_202x120_1e6cf26b-f9cc-4839-af43-1eecbd54ce7f.jpg",
        "publicationDate": "22.01.10"
    },
    {
        "title": "215. P.R.R.W",
        "url": "https://comic.naver.com/webtoon/detail?titleId=702608&no=215&week=tue",
        "imageUrl": "https://image-comic.pstatic.net/webtoon/702608/215/thumbnail_202x120_33e4481b-6a29-46f0-b2b3-d28ba2004005.jpg",
        "publicationDate": "22.01.03"
    },
    {
        "title": "214. 내가 맞았어",
        "url": "https://comic.naver.com/webtoon/detail?titleId=702608&no=214&week=tue",
        "imageUrl": "https://image-comic.pstatic.net/webtoon/702608/214/thumbnail_202x120_aabe4b5d-128e-4c84-afef-d680ae471f18.jpg",
        "publicationDate": "21.12.27"
    },
    {
        "title": "213. by the way",
        "url": "https://comic.naver.com/webtoon/detail?titleId=702608&no=213&week=tue",
        "imageUrl": "https://image-comic.pstatic.net/webtoon/702608/213/thumbnail_202x120_56c66193-e81c-4245-9484-854b6fd86174.jpg",
        "publicationDate": "21.12.20"
    },
    {
        "title": "212. 제 이름은",
        "url": "https://comic.naver.com/webtoon/detail?titleId=702608&no=212&week=tue",
        "imageUrl": "https://image-comic.pstatic.net/webtoon/702608/212/thumbnail_202x120_d01a49fb-2c20-4553-b741-f0ae932e125a.jpg",
        "publicationDate": "21.12.13"
    },
    {
        "title": "211. 귀찮아 죽겠네",
        "url": "https://comic.naver.com/webtoon/detail?titleId=702608&no=211&week=tue",
        "imageUrl": "https://image-comic.pstatic.net/webtoon/702608/211/thumbnail_202x120_b3313ff6-f441-48e9-a777-41f2794af253.jpg",
        "publicationDate": "21.12.06"
    },
    {
        "title": "210. 운명",
        "url": "https://comic.naver.com/webtoon/detail?titleId=702608&no=210&week=tue",
        "imageUrl": "https://image-comic.pstatic.net/webtoon/702608/210/thumbnail_202x120_3553e3a3-a3c7-471d-93cd-889e572393d0.jpg",
        "publicationDate": "21.11.29"
    },
    {
        "title": "209. 다시 랜덤채팅에서",
        "url": "https://comic.naver.com/webtoon/detail?titleId=702608&no=209&week=tue",
        "imageUrl": "https://image-comic.pstatic.net/webtoon/702608/209/thumbnail_202x120_11f17390-3932-4bb6-8770-96522bdb8283.jpg",
        "publicationDate": "21.11.22"
    },
    {
        "title": "208. 너는 어떻게 지내니",
        "url": "https://comic.naver.com/webtoon/detail?titleId=702608&no=208&week=tue",
        "imageUrl": "https://image-comic.pstatic.net/webtoon/702608/208/thumbnail_202x120_0b643549-7898-4cac-ab5f-5cd1c70fc417.jpg",
        "publicationDate": "21.11.15"
    },
    {
        "title": "207. 사랑",
        "url": "https://comic.naver.com/webtoon/detail?titleId=702608&no=207&week=tue",
        "imageUrl": "https://image-comic.pstatic.net/webtoon/702608/207/thumbnail_202x120_e5f59bcb-5118-4bf2-9686-cbe7c0b0b841.jpg",
        "publicationDate": "21.11.08"
    },
    {
        "title": "206. 너만이 이겨낼 수 있는 슬픔",
        "url": "https://comic.naver.com/webtoon/detail?titleId=702608&no=206&week=tue",
        "imageUrl": "https://image-comic.pstatic.net/webtoon/702608/206/thumbnail_202x120_15771f9d-918d-4972-b485-6fc18aa68bc8.jpg",
        "publicationDate": "21.11.01"
    },
    {
        "title": "205. 운명처럼",
        "url": "https://comic.naver.com/webtoon/detail?titleId=702608&no=205&week=tue",
        "imageUrl": "https://image-comic.pstatic.net/webtoon/702608/205/thumbnail_202x120_ce024afd-e427-4d96-88f8-b97bbe141d5c.jpg",
        "publicationDate": "21.10.25"
    },
    {
        "title": "204. 추억이면",
        "url": "https://comic.naver.com/webtoon/detail?titleId=702608&no=204&week=tue",
        "imageUrl": "https://image-comic.pstatic.net/webtoon/702608/204/thumbnail_202x120_688bc68e-8772-469b-82ad-4c73f304c560.jpg",
        "publicationDate": "21.10.18"
    },
    {
        "title": "203. 너는 항상",
        "url": "https://comic.naver.com/webtoon/detail?titleId=702608&no=203&week=tue",
        "imageUrl": "https://image-comic.pstatic.net/webtoon/702608/203/thumbnail_202x120_ba2d2538-2945-4a0e-a391-739ecf6b5354.jpg",
        "publicationDate": "21.10.11"
    },
    {
        "title": "202. Who is villain?",
        "url": "https://comic.naver.com/webtoon/detail?titleId=702608&no=202&week=tue",
        "imageUrl": "https://image-comic.pstatic.net/webtoon/702608/202/thumbnail_202x120_f3ef518d-81a5-499c-af86-2e19009470b2.jpg",
        "publicationDate": "21.10.04"
    },
    {
        "title": "201. 헤어지고 싶어?",
        "url": "https://comic.naver.com/webtoon/detail?titleId=702608&no=201&week=tue",
        "imageUrl": "https://image-comic.pstatic.net/webtoon/702608/201/thumbnail_202x120_8ae9d7a2-da73-410f-9398-c6250c2339b1.jpg",
        "publicationDate": "21.09.27"
    },
    {
        "title": "200. 세상은 좁다 + 200화 특집편",
        "url": "https://comic.naver.com/webtoon/detail?titleId=702608&no=200&week=tue",
        "imageUrl": "https://image-comic.pstatic.net/webtoon/702608/200/thumbnail_202x120_1d1d2f38-13be-4017-ae66-c235089438c6.jpg",
        "publicationDate": "21.09.20"
    },
    {
        "title": "199. 좋아하니까",
        "url": "https://comic.naver.com/webtoon/detail?titleId=702608&no=199&week=tue",
        "imageUrl": "https://image-comic.pstatic.net/webtoon/702608/199/thumbnail_202x120_360d845c-6c65-4c72-9109-19f65ced5748.jpg",
        "publicationDate": "21.09.13"
    },
    {
        "title": "198. 믿음",
        "url": "https://comic.naver.com/webtoon/detail?titleId=702608&no=198&week=tue",
        "imageUrl": "https://image-comic.pstatic.net/webtoon/702608/198/thumbnail_202x120_7cd17728-4048-4441-9bea-1acd6d1d317d.jpg",
        "publicationDate": "21.09.06"
    },
    {
        "title": "197. 내로남불",
        "url": "https://comic.naver.com/webtoon/detail?titleId=702608&no=197&week=tue",
        "imageUrl": "https://image-comic.pstatic.net/webtoon/702608/197/thumbnail_202x120_57c9d6ff-b0e7-4732-8b09-441905db9a97.jpg",
        "publicationDate": "21.08.30"
    },
    {
        "title": "196. 깊은 밤",
        "url": "https://comic.naver.com/webtoon/detail?titleId=702608&no=196&week=tue",
        "imageUrl": "https://image-comic.pstatic.net/webtoon/702608/196/thumbnail_202x120_120e2bac-b4c9-4df7-ab3f-5a97c524d01b.jpg",
        "publicationDate": "21.08.23"
    },
    {
        "title": "195. 밤",
        "url": "https://comic.naver.com/webtoon/detail?titleId=702608&no=195&week=tue",
        "imageUrl": "https://image-comic.pstatic.net/webtoon/702608/195/thumbnail_202x120_08c7b4c9-1253-4230-bacf-a0372a72b5ba.jpg",
        "publicationDate": "21.08.16"
    },
    {
        "title": "194. 두근두근",
        "url": "https://comic.naver.com/webtoon/detail?titleId=702608&no=194&week=tue",
        "imageUrl": "https://image-comic.pstatic.net/webtoon/702608/194/thumbnail_202x120_aabb4f60-7c79-44a7-864a-3b75281e24a3.jpg",
        "publicationDate": "21.08.09"
    },
    {
        "title": "193. 새로운 물결",
        "url": "https://comic.naver.com/webtoon/detail?titleId=702608&no=193&week=tue",
        "imageUrl": "https://image-comic.pstatic.net/webtoon/702608/193/thumbnail_202x120_dd55d511-9716-49e1-85e8-f646e969b1f6.jpg",
        "publicationDate": "21.08.02"
    },
    {
        "title": "192. VS????",
        "url": "https://comic.naver.com/webtoon/detail?titleId=702608&no=192&week=tue",
        "imageUrl": "https://image-comic.pstatic.net/webtoon/702608/192/thumbnail_202x120_b01278eb-c996-4637-8a3d-4c7e857416b7.jpg",
        "publicationDate": "21.07.26"
    },
    {
        "title": "191. VS임대현?",
        "url": "https://comic.naver.com/webtoon/detail?titleId=702608&no=191&week=tue",
        "imageUrl": "https://image-comic.pstatic.net/webtoon/702608/191/thumbnail_202x120_a5da60f2-8788-4ee8-9b6a-6a2a2c217e8d.jpg",
        "publicationDate": "21.07.19"
    },
    {
        "title": "190. VS임대현",
        "url": "https://comic.naver.com/webtoon/detail?titleId=702608&no=190&week=tue",
        "imageUrl": "https://image-comic.pstatic.net/webtoon/702608/190/thumbnail_202x120_a6bfe599-a7fc-4662-9e5f-6e02602aa1ea.jpg",
        "publicationDate": "21.07.12"
    },
    {
        "title": "189. 임대현",
        "url": "https://comic.naver.com/webtoon/detail?titleId=702608&no=189&week=tue",
        "imageUrl": "https://image-comic.pstatic.net/webtoon/702608/189/thumbnail_202x120_686e61bc-9a11-42cb-b17e-06c5d7c15299.jpg",
        "publicationDate": "21.07.05"
    },
    {
        "title": "188. 숨을 쉬다",
        "url": "https://comic.naver.com/webtoon/detail?titleId=702608&no=188&week=tue",
        "imageUrl": "https://image-comic.pstatic.net/webtoon/702608/188/thumbnail_202x120_7a6a7c36-b5a1-473d-847e-79844def182f.jpg",
        "publicationDate": "21.06.28"
    },
    {
        "title": "187. 세상은 둘로 나뉘지 않는다",
        "url": "https://comic.naver.com/webtoon/detail?titleId=702608&no=187&week=tue",
        "imageUrl": "https://image-comic.pstatic.net/webtoon/702608/187/thumbnail_202x120_29f288b3-f1c9-4109-915e-d35c9f1b1f6f.jpg",
        "publicationDate": "21.06.21"
    },
    {
        "title": "186. 싸움을 위한 싸움",
        "url": "https://comic.naver.com/webtoon/detail?titleId=702608&no=186&week=tue",
        "imageUrl": "https://image-comic.pstatic.net/webtoon/702608/186/thumbnail_202x120_faa62ebc-9bc0-463a-8b93-7d45e7d7a467.jpg",
        "publicationDate": "21.06.14"
    },
    {
        "title": "185. POSITION",
        "url": "https://comic.naver.com/webtoon/detail?titleId=702608&no=185&week=tue",
        "imageUrl": "https://image-comic.pstatic.net/webtoon/702608/185/thumbnail_202x120_e7e679b6-e633-487d-8b6c-10a66e183c21.jpg",
        "publicationDate": "21.06.07"
    },
    {
        "title": "184. 좋은 현상",
        "url": "https://comic.naver.com/webtoon/detail?titleId=702608&no=184&week=tue",
        "imageUrl": "https://image-comic.pstatic.net/webtoon/702608/184/thumbnail_202x120_188fbdd4-6f3e-492f-a476-248ba91d2f63.jpg",
        "publicationDate": "21.05.31"
    },
    {
        "title": "183. 우린 지금 물 위를 가고 있어",
        "url": "https://comic.naver.com/webtoon/detail?titleId=702608&no=183&week=tue",
        "imageUrl": "https://image-comic.pstatic.net/webtoon/702608/183/thumbnail_202x120_d04565fc-167c-4026-b008-fc92c48ba2db.jpg",
        "publicationDate": "21.05.24"
    },
    {
        "title": "182. 소름 돋는다",
        "url": "https://comic.naver.com/webtoon/detail?titleId=702608&no=182&week=tue",
        "imageUrl": "https://image-comic.pstatic.net/webtoon/702608/182/thumbnail_202x120_5a04be42-c052-4739-921a-6df5bfc49b4c.jpg",
        "publicationDate": "21.05.17"
    },
    {
        "title": "181. 개과천선",
        "url": "https://comic.naver.com/webtoon/detail?titleId=702608&no=181&week=tue",
        "imageUrl": "https://image-comic.pstatic.net/webtoon/702608/181/thumbnail_202x120_b31fd17a-77f7-4157-a5bd-18d44b0861e3.jpg",
        "publicationDate": "21.05.10"
    },
    {
        "title": "180. 멀리는 안나간다",
        "url": "https://comic.naver.com/webtoon/detail?titleId=702608&no=180&week=tue",
        "imageUrl": "https://image-comic.pstatic.net/webtoon/702608/180/thumbnail_202x120_b88db814-a90b-4b31-a033-7e8bbf4d14aa.jpg",
        "publicationDate": "21.05.03"
    },
    {
        "title": "179. 그 후 그들은",
        "url": "https://comic.naver.com/webtoon/detail?titleId=702608&no=179&week=tue",
        "imageUrl": "https://image-comic.pstatic.net/webtoon/702608/179/thumbnail_202x120_deadc2f2-9e42-4cab-94b4-69905105f680.jpg",
        "publicationDate": "21.04.26"
    },
    {
        "title": "178. 나는 너를 이해할 수 없다",
        "url": "https://comic.naver.com/webtoon/detail?titleId=702608&no=178&week=tue",
        "imageUrl": "https://image-comic.pstatic.net/webtoon/702608/178/thumbnail_202x120_2b82bc47-6cbc-43c4-b2dc-43a26572c680.jpg",
        "publicationDate": "21.04.19"
    },
    {
        "title": "177. 사람의 기준",
        "url": "https://comic.naver.com/webtoon/detail?titleId=702608&no=177&week=tue",
        "imageUrl": "https://image-comic.pstatic.net/webtoon/702608/177/thumbnail_202x120_39900241-bfcf-44f2-bb83-f0c854dc87c2.jpg",
        "publicationDate": "21.04.12"
    },
    {
        "title": "176. Life goes on",
        "url": "https://comic.naver.com/webtoon/detail?titleId=702608&no=176&week=tue",
        "imageUrl": "https://image-comic.pstatic.net/webtoon/702608/176/thumbnail_202x120_d4a94a8f-fe9a-47eb-9ab8-45cd6bba5b4b.jpg",
        "publicationDate": "21.04.05"
    },
    {
        "title": "175. 모잠비크드릴",
        "url": "https://comic.naver.com/webtoon/detail?titleId=702608&no=175&week=tue",
        "imageUrl": "https://image-comic.pstatic.net/webtoon/702608/175/thumbnail_202x120_beac571f-39d8-4a19-ba9a-b260b2ec12f1.jpg",
        "publicationDate": "21.03.29"
    },
    {
        "title": "174. 강한 사람",
        "url": "https://comic.naver.com/webtoon/detail?titleId=702608&no=174&week=tue",
        "imageUrl": "https://image-comic.pstatic.net/webtoon/702608/174/thumbnail_202x120_e4b52f00-2555-430a-8794-c51cde899fba.jpg",
        "publicationDate": "21.03.22"
    },
    {
        "title": "173. 인생",
        "url": "https://comic.naver.com/webtoon/detail?titleId=702608&no=173&week=tue",
        "imageUrl": "https://image-comic.pstatic.net/webtoon/702608/173/thumbnail_202x120_b9a9ee7e-ac35-4465-a52c-94d42884ce72.jpg",
        "publicationDate": "21.03.15"
    },
    {
        "title": "172. 범죄의 형태",
        "url": "https://comic.naver.com/webtoon/detail?titleId=702608&no=172&week=tue",
        "imageUrl": "https://image-comic.pstatic.net/webtoon/702608/172/thumbnail_202x120_06c0149a-4982-4e1a-987e-ac82bf2b1b23.jpg",
        "publicationDate": "21.03.08"
    },
    {
        "title": "171. 범죄의 탄생",
        "url": "https://comic.naver.com/webtoon/detail?titleId=702608&no=171&week=tue",
        "imageUrl": "https://image-comic.pstatic.net/webtoon/702608/171/thumbnail_202x120_3af936eb-2ceb-44f4-a9fd-8fec17c3bd7c.jpg",
        "publicationDate": "21.03.01"
    },
    {
        "title": "170. BLACK",
        "url": "https://comic.naver.com/webtoon/detail?titleId=702608&no=170&week=tue",
        "imageUrl": "https://image-comic.pstatic.net/webtoon/702608/170/thumbnail_202x120_dea0e6fe-d8a5-4e7c-932f-f05d9280f512.jpg",
        "publicationDate": "21.02.22"
    },
    {
        "title": "169. 사람들",
        "url": "https://comic.naver.com/webtoon/detail?titleId=702608&no=169&week=tue",
        "imageUrl": "https://image-comic.pstatic.net/webtoon/702608/169/thumbnail_202x120_c320c38a-18c3-4cdf-ba45-463b6cc264ec.jpg",
        "publicationDate": "21.02.15"
    },
    {
        "title": "168. be born evil",
        "url": "https://comic.naver.com/webtoon/detail?titleId=702608&no=168&week=tue",
        "imageUrl": "https://image-comic.pstatic.net/webtoon/702608/168/thumbnail_202x120_b6e0d84e-acca-4d87-b129-4a7c1e4bdd8c.jpg",
        "publicationDate": "21.02.08"
    },
    {
        "title": "167. 죽어버려라",
        "url": "https://comic.naver.com/webtoon/detail?titleId=702608&no=167&week=tue",
        "imageUrl": "https://image-comic.pstatic.net/webtoon/702608/167/thumbnail_202x120_212ed9e3-ff84-4173-97da-33e5617b5ac6.jpg",
        "publicationDate": "21.02.01"
    },
    {
        "title": "166. HUNT",
        "url": "https://comic.naver.com/webtoon/detail?titleId=702608&no=166&week=tue",
        "imageUrl": "https://image-comic.pstatic.net/webtoon/702608/166/thumbnail_202x120_db072918-cf07-4a48-b923-a817cbef31a2.jpg",
        "publicationDate": "21.01.25"
    },
    {
        "title": "165. ANTI",
        "url": "https://comic.naver.com/webtoon/detail?titleId=702608&no=165&week=tue",
        "imageUrl": "https://image-comic.pstatic.net/webtoon/702608/165/thumbnail_202x120_1986dc6e-0140-4ebf-b653-b4d6f2b36f4c.jpg",
        "publicationDate": "21.01.18"
    },
    {
        "title": "164. 추론",
        "url": "https://comic.naver.com/webtoon/detail?titleId=702608&no=164&week=tue",
        "imageUrl": "https://image-comic.pstatic.net/webtoon/702608/164/thumbnail_202x120_973bdcf5-0c38-4a75-9659-796538933346.jpg",
        "publicationDate": "21.01.11"
    },
    {
        "title": "163. 유인",
        "url": "https://comic.naver.com/webtoon/detail?titleId=702608&no=163&week=tue",
        "imageUrl": "https://image-comic.pstatic.net/webtoon/702608/163/thumbnail_202x120_290149cc-75f6-4977-aeaf-0169ae6cb2e9.jpg",
        "publicationDate": "21.01.04"
    },
    {
        "title": "162. 뒤끝",
        "url": "https://comic.naver.com/webtoon/detail?titleId=702608&no=162&week=tue",
        "imageUrl": "https://image-comic.pstatic.net/webtoon/702608/162/thumbnail_202x120_d02530d9-5e07-4ece-a805-3cfc7041d684.jpg",
        "publicationDate": "20.12.28"
    },
    {
        "title": "161. 남친대행",
        "url": "https://comic.naver.com/webtoon/detail?titleId=702608&no=161&week=tue",
        "imageUrl": "https://image-comic.pstatic.net/webtoon/702608/161/thumbnail_202x120_8b045be1-a521-4bfb-b0a5-525ff3af8233.jpg",
        "publicationDate": "20.12.21"
    },
    {
        "title": "160. 감정쓰레기통",
        "url": "https://comic.naver.com/webtoon/detail?titleId=702608&no=160&week=tue",
        "imageUrl": "https://image-comic.pstatic.net/webtoon/702608/160/thumbnail_202x120_1375d520-a19d-469a-aa84-f6fc5e7774f3.jpg",
        "publicationDate": "20.12.14"
    },
    {
        "title": "159. 순수한 의문",
        "url": "https://comic.naver.com/webtoon/detail?titleId=702608&no=159&week=tue",
        "imageUrl": "https://image-comic.pstatic.net/webtoon/702608/159/thumbnail_202x120_f407f945-8213-4cff-b8a6-4e7ba96a3449.jpg",
        "publicationDate": "20.12.07"
    },
    {
        "title": "158. 반가워",
        "url": "https://comic.naver.com/webtoon/detail?titleId=702608&no=158&week=tue",
        "imageUrl": "https://image-comic.pstatic.net/webtoon/702608/158/thumbnail_202x120_f84db0f8-5719-4f5b-805c-1febe4896e38.jpg",
        "publicationDate": "20.11.30"
    },
    {
        "title": "157. 만남의 시간",
        "url": "https://comic.naver.com/webtoon/detail?titleId=702608&no=157&week=tue",
        "imageUrl": "https://image-comic.pstatic.net/webtoon/702608/157/thumbnail_202x120_db08754c-82c6-4d95-ad10-ce7622d8dd67.jpg",
        "publicationDate": "20.11.23"
    },
    {
        "title": "156. 멘토",
        "url": "https://comic.naver.com/webtoon/detail?titleId=702608&no=156&week=tue",
        "imageUrl": "https://image-comic.pstatic.net/webtoon/702608/156/thumbnail_202x120_320c8a1a-d273-4b24-b46a-25edefc927fa.jpg",
        "publicationDate": "20.11.16"
    },
    {
        "title": "155. 더 이상",
        "url": "https://comic.naver.com/webtoon/detail?titleId=702608&no=155&week=tue",
        "imageUrl": "https://image-comic.pstatic.net/webtoon/702608/155/thumbnail_202x120_9b7179f2-c2b9-4a30-a2a9-7382bb236ca0.jpg",
        "publicationDate": "20.11.09"
    },
    {
        "title": "154. 몇 달 후",
        "url": "https://comic.naver.com/webtoon/detail?titleId=702608&no=154&week=tue",
        "imageUrl": "https://image-comic.pstatic.net/webtoon/702608/154/thumbnail_202x120_385daab6-87ac-4cbe-afd1-aecc864c085f.jpg",
        "publicationDate": "20.11.02"
    },
    {
        "title": "153. 동행",
        "url": "https://comic.naver.com/webtoon/detail?titleId=702608&no=153&week=tue",
        "imageUrl": "https://image-comic.pstatic.net/webtoon/702608/153/thumbnail_202x120_a4bf52c0-e0a7-4fef-9321-2f609892500d.jpg",
        "publicationDate": "20.10.26"
    },
    {
        "title": "152. 자격",
        "url": "https://comic.naver.com/webtoon/detail?titleId=702608&no=152&week=tue",
        "imageUrl": "https://image-comic.pstatic.net/webtoon/702608/152/thumbnail_202x120_f4fa3a52-4b3b-4fe2-b8a9-7a30bc4e92bf.jpg",
        "publicationDate": "20.10.19"
    },
    {
        "title": "151. 뒤를 돌아보면",
        "url": "https://comic.naver.com/webtoon/detail?titleId=702608&no=151&week=tue",
        "imageUrl": "https://image-comic.pstatic.net/webtoon/702608/151/thumbnail_202x120_a1682fcc-12c0-4d1a-ab28-cffbd466e806.jpg",
        "publicationDate": "20.10.12"
    },
    {
        "title": "150. 고요한 바다",
        "url": "https://comic.naver.com/webtoon/detail?titleId=702608&no=150&week=tue",
        "imageUrl": "https://image-comic.pstatic.net/webtoon/702608/150/thumbnail_202x120_feba5042-0068-4578-919a-b79a9985962d.jpg",
        "publicationDate": "20.10.05"
    },
    {
        "title": "149. make a chance",
        "url": "https://comic.naver.com/webtoon/detail?titleId=702608&no=149&week=tue",
        "imageUrl": "https://image-comic.pstatic.net/webtoon/702608/149/thumbnail_202x120_bd157e50-53ea-4766-afa5-b7654386c921.jpg",
        "publicationDate": "20.09.28"
    },
    {
        "title": "148. 자기모순",
        "url": "https://comic.naver.com/webtoon/detail?titleId=702608&no=148&week=tue",
        "imageUrl": "https://image-comic.pstatic.net/webtoon/702608/148/thumbnail_202x120_42f6bd1c-b016-4f7f-b693-96894b719339.jpg",
        "publicationDate": "20.09.21"
    },
    {
        "title": "147. 해일(3)",
        "url": "https://comic.naver.com/webtoon/detail?titleId=702608&no=147&week=tue",
        "imageUrl": "https://image-comic.pstatic.net/webtoon/702608/147/thumbnail_202x120_5b70df14-de1c-425c-be21-aadb2bb98215.jpg",
        "publicationDate": "20.09.07"
    },
    {
        "title": "146. 해일(2)",
        "url": "https://comic.naver.com/webtoon/detail?titleId=702608&no=146&week=tue",
        "imageUrl": "https://image-comic.pstatic.net/webtoon/702608/146/thumbnail_202x120_d2a4dfee-3904-4dc7-9e2f-4ea09c587aa1.jpg",
        "publicationDate": "20.08.31"
    },
    {
        "title": "145. 해일(1)",
        "url": "https://comic.naver.com/webtoon/detail?titleId=702608&no=145&week=tue",
        "imageUrl": "https://image-comic.pstatic.net/webtoon/702608/145/thumbnail_202x120_c3ea9cb1-5dd4-4c10-854d-100f724edfee.jpg",
        "publicationDate": "20.08.24"
    },
    {
        "title": "144. 파도(3)",
        "url": "https://comic.naver.com/webtoon/detail?titleId=702608&no=144&week=tue",
        "imageUrl": "https://image-comic.pstatic.net/webtoon/702608/144/thumbnail_202x120_8f13131f-a624-4a4c-b887-7b2253bdb635.jpg",
        "publicationDate": "20.08.17"
    },
    {
        "title": "143. 파도(2)",
        "url": "https://comic.naver.com/webtoon/detail?titleId=702608&no=143&week=tue",
        "imageUrl": "https://image-comic.pstatic.net/webtoon/702608/143/thumbnail_202x120_41d30fea-ef9d-41f5-9476-98b05808f87f.jpg",
        "publicationDate": "20.08.10"
    },
    {
        "title": "142. 파도(1)",
        "url": "https://comic.naver.com/webtoon/detail?titleId=702608&no=142&week=tue",
        "imageUrl": "https://image-comic.pstatic.net/webtoon/702608/142/thumbnail_202x120_7f545e0c-3fd5-4d0c-baaf-6c7d2850c994.jpg",
        "publicationDate": "20.08.03"
    },
    {
        "title": "141. 바다이야기",
        "url": "https://comic.naver.com/webtoon/detail?titleId=702608&no=141&week=tue",
        "imageUrl": "https://image-comic.pstatic.net/webtoon/702608/141/thumbnail_202x120_c06f83aa-034f-44b5-b782-35d5b175f3a4.jpg",
        "publicationDate": "20.07.27"
    },
    {
        "title": "140. silhouette",
        "url": "https://comic.naver.com/webtoon/detail?titleId=702608&no=140&week=tue",
        "imageUrl": "https://image-comic.pstatic.net/webtoon/702608/140/thumbnail_202x120_1dcd92da-a5fa-4896-b995-5398ba7c2e39.jpg",
        "publicationDate": "20.07.20"
    },
    {
        "title": "139. 자유의지",
        "url": "https://comic.naver.com/webtoon/detail?titleId=702608&no=139&week=tue",
        "imageUrl": "https://image-comic.pstatic.net/webtoon/702608/139/thumbnail_202x120_cb54761c-4521-4d01-85cc-d92e44e97378.jpg",
        "publicationDate": "20.07.13"
    },
    {
        "title": "138. 판단",
        "url": "https://comic.naver.com/webtoon/detail?titleId=702608&no=138&week=tue",
        "imageUrl": "https://image-comic.pstatic.net/webtoon/702608/138/thumbnail_202x120_60b6b62f-6bd3-43ff-8369-3f7460e6a2e1.jpg",
        "publicationDate": "20.07.06"
    },
    {
        "title": "137. 연쇄",
        "url": "https://comic.naver.com/webtoon/detail?titleId=702608&no=137&week=tue",
        "imageUrl": "https://image-comic.pstatic.net/webtoon/702608/137/thumbnail_202x120_40e74c12-871a-41f7-930d-826604470504.jpg",
        "publicationDate": "20.06.29"
    },
    {
        "title": "136. 결과",
        "url": "https://comic.naver.com/webtoon/detail?titleId=702608&no=136&week=tue",
        "imageUrl": "https://image-comic.pstatic.net/webtoon/702608/136/thumbnail_202x120_505dba17-1c31-4f34-bda7-8c49fbe22f05.jpg",
        "publicationDate": "20.06.22"
    },
    {
        "title": "135. 증명",
        "url": "https://comic.naver.com/webtoon/detail?titleId=702608&no=135&week=tue",
        "imageUrl": "https://image-comic.pstatic.net/webtoon/702608/135/thumbnail_202x120_213f3d8b-8e6c-44c9-a634-eb5f9f61db23.jpg",
        "publicationDate": "20.06.15"
    },
    {
        "title": "134. 결단",
        "url": "https://comic.naver.com/webtoon/detail?titleId=702608&no=134&week=tue",
        "imageUrl": "https://image-comic.pstatic.net/webtoon/702608/134/thumbnail_202x120_d4100b10-1560-435c-9aae-eda6686192f4.jpg",
        "publicationDate": "20.06.08"
    },
    {
        "title": "133. UPCOMING",
        "url": "https://comic.naver.com/webtoon/detail?titleId=702608&no=133&week=tue",
        "imageUrl": "https://image-comic.pstatic.net/webtoon/702608/133/thumbnail_202x120_8d129a42-8861-4367-8932-be7121219a52.jpg",
        "publicationDate": "20.06.01"
    },
    {
        "title": "132. Love Letter",
        "url": "https://comic.naver.com/webtoon/detail?titleId=702608&no=132&week=tue",
        "imageUrl": "https://image-comic.pstatic.net/webtoon/702608/132/thumbnail_202x120_46111755-671b-4c5f-9828-4d5f877740e6.jpg",
        "publicationDate": "20.05.25"
    },
    {
        "title": "131. 의지할 곳",
        "url": "https://comic.naver.com/webtoon/detail?titleId=702608&no=131&week=tue",
        "imageUrl": "https://image-comic.pstatic.net/webtoon/702608/131/thumbnail_202x120_a5512622-71d6-4a7d-82dd-f5a3dc17fe8d.jpg",
        "publicationDate": "20.05.18"
    },
    {
        "title": "130. 영원한 건 없다",
        "url": "https://comic.naver.com/webtoon/detail?titleId=702608&no=130&week=tue",
        "imageUrl": "https://image-comic.pstatic.net/webtoon/702608/130/thumbnail_202x120_b7df7ca9-228d-46b9-b7cf-1ae1bee69020.jpg",
        "publicationDate": "20.05.11"
    },
    {
        "title": "129. 알려줘",
        "url": "https://comic.naver.com/webtoon/detail?titleId=702608&no=129&week=tue",
        "imageUrl": "https://image-comic.pstatic.net/webtoon/702608/129/thumbnail_202x120_275a11cd-114a-4ad7-9dda-8e7db464af9d.jpg",
        "publicationDate": "20.05.04"
    },
    {
        "title": "128. Approach",
        "url": "https://comic.naver.com/webtoon/detail?titleId=702608&no=128&week=tue",
        "imageUrl": "https://image-comic.pstatic.net/webtoon/702608/128/thumbnail_202x120_797fadb9-14bf-42ef-a2c4-ac0d1375a676.jpg",
        "publicationDate": "20.04.27"
    },
    {
        "title": "127. 좋아하는 사람에게 좋아했다고 말하지는 않는다.",
        "url": "https://comic.naver.com/webtoon/detail?titleId=702608&no=127&week=tue",
        "imageUrl": "https://image-comic.pstatic.net/webtoon/702608/127/thumbnail_202x120_2c711cc6-984d-4c92-a041-93b26b579e0b.jpg",
        "publicationDate": "20.04.20"
    },
    {
        "title": "126. 너의 곁에서, 주변에서",
        "url": "https://comic.naver.com/webtoon/detail?titleId=702608&no=126&week=tue",
        "imageUrl": "https://image-comic.pstatic.net/webtoon/702608/126/thumbnail_202x120_0fb1958d-4468-4bf9-99b3-167c84a74125.jpg",
        "publicationDate": "20.04.13"
    },
    {
        "title": "125. 말을 잘 못하는 아이",
        "url": "https://comic.naver.com/webtoon/detail?titleId=702608&no=125&week=tue",
        "imageUrl": "https://image-comic.pstatic.net/webtoon/702608/125/thumbnail_202x120_3ad5423e-6cbc-4b78-951a-9b1e813dd78f.jpg",
        "publicationDate": "20.04.06"
    },
    {
        "title": "124. 아이들",
        "url": "https://comic.naver.com/webtoon/detail?titleId=702608&no=124&week=tue",
        "imageUrl": "https://image-comic.pstatic.net/webtoon/702608/124/thumbnail_202x120_dc38dd27-e4a6-477c-b8d6-ce48b644e9da.jpg",
        "publicationDate": "20.03.30"
    },
    {
        "title": "123. 부탁",
        "url": "https://comic.naver.com/webtoon/detail?titleId=702608&no=123&week=tue",
        "imageUrl": "https://image-comic.pstatic.net/webtoon/702608/123/thumbnail_202x120_b3bc7356-03af-47e7-b72f-2b2c7ed3aee9.jpg",
        "publicationDate": "20.03.23"
    },
    {
        "title": "122. 그만",
        "url": "https://comic.naver.com/webtoon/detail?titleId=702608&no=122&week=tue",
        "imageUrl": "https://image-comic.pstatic.net/webtoon/702608/122/thumbnail_202x120_2b0960ac-14d5-45d6-ae09-2fc39b5b0c7a.jpg",
        "publicationDate": "20.03.16"
    },
    {
        "title": "121. 나쁜놈",
        "url": "https://comic.naver.com/webtoon/detail?titleId=702608&no=121&week=tue",
        "imageUrl": "https://image-comic.pstatic.net/webtoon/702608/121/thumbnail_202x120_f638aab7-140e-401f-83f3-e97bbf4b38ee.jpg",
        "publicationDate": "20.03.09"
    },
    {
        "title": "120. 어?",
        "url": "https://comic.naver.com/webtoon/detail?titleId=702608&no=120&week=tue",
        "imageUrl": "https://image-comic.pstatic.net/webtoon/702608/120/thumbnail_202x120_ed58bb51-fc7d-4404-8d39-45cea18e9b5c.jpg",
        "publicationDate": "20.03.02"
    },
    {
        "title": "119. 점점",
        "url": "https://comic.naver.com/webtoon/detail?titleId=702608&no=119&week=tue",
        "imageUrl": "https://image-comic.pstatic.net/webtoon/702608/119/thumbnail_202x120_b4d9053c-1c6c-4413-bf20-313bd64ef821.jpg",
        "publicationDate": "20.02.24"
    },
    {
        "title": "118. 준우가 다가가는 방법",
        "url": "https://comic.naver.com/webtoon/detail?titleId=702608&no=118&week=tue",
        "imageUrl": "https://image-comic.pstatic.net/webtoon/702608/118/thumbnail_202x120_ac866bb1-5511-43df-8451-f65375413db9.jpg",
        "publicationDate": "20.02.17"
    },
    {
        "title": "117. 진실은 지금",
        "url": "https://comic.naver.com/webtoon/detail?titleId=702608&no=117&week=tue",
        "imageUrl": "https://image-comic.pstatic.net/webtoon/702608/117/thumbnail_202x120_71350098-cfd9-4170-87ac-8c4a053b3c9b.jpg",
        "publicationDate": "20.02.10"
    },
    {
        "title": "116. 하고 싶은 말",
        "url": "https://comic.naver.com/webtoon/detail?titleId=702608&no=116&week=tue",
        "imageUrl": "https://image-comic.pstatic.net/webtoon/702608/116/thumbnail_202x120_403a64a3-2d42-4777-932c-37b610c8c52e.jpg",
        "publicationDate": "20.02.03"
    },
    {
        "title": "115. 너에게 가는 길",
        "url": "https://comic.naver.com/webtoon/detail?titleId=702608&no=115&week=tue",
        "imageUrl": "https://image-comic.pstatic.net/webtoon/702608/115/thumbnail_202x120_27c0f0ea-b1db-4047-b7a9-0813a8243ee7.jpg",
        "publicationDate": "20.01.27"
    },
    {
        "title": "114. 주변",
        "url": "https://comic.naver.com/webtoon/detail?titleId=702608&no=114&week=tue",
        "imageUrl": "https://image-comic.pstatic.net/webtoon/702608/114/thumbnail_202x120_5b2c9147-4e9a-49d4-89d6-b87e3c290c83.jpg",
        "publicationDate": "20.01.20"
    },
    {
        "title": "113. RUMOR",
        "url": "https://comic.naver.com/webtoon/detail?titleId=702608&no=113&week=tue",
        "imageUrl": "https://image-comic.pstatic.net/webtoon/702608/113/thumbnail_202x120_1da30b09-3ac6-4735-8fdb-29c101f04ef0.jpg",
        "publicationDate": "20.01.13"
    },
    {
        "title": "112. Never Backdown 2",
        "url": "https://comic.naver.com/webtoon/detail?titleId=702608&no=112&week=tue",
        "imageUrl": "https://image-comic.pstatic.net/webtoon/702608/112/thumbnail_202x120_5b8d3dd5-bc00-4072-905f-523c1fe2616b.jpg",
        "publicationDate": "20.01.06"
    },
    {
        "title": "111. Never Backdown",
        "url": "https://comic.naver.com/webtoon/detail?titleId=702608&no=111&week=tue",
        "imageUrl": "https://image-comic.pstatic.net/webtoon/702608/111/thumbnail_202x120_cae9e2ce-f083-4a4f-8640-9984621f53a5.jpg",
        "publicationDate": "19.12.30"
    },
    {
        "title": "110. 지금의 넌",
        "url": "https://comic.naver.com/webtoon/detail?titleId=702608&no=110&week=tue",
        "imageUrl": "https://image-comic.pstatic.net/webtoon/702608/110/thumbnail_202x120_0c882cab-1654-447d-b36c-a4faf1f3a1ef.jpg",
        "publicationDate": "19.12.23"
    },
    {
        "title": "109. 지금의 난",
        "url": "https://comic.naver.com/webtoon/detail?titleId=702608&no=109&week=tue",
        "imageUrl": "https://image-comic.pstatic.net/webtoon/702608/109/thumbnail_202x120_b28923bb-2614-4176-b181-27a570983b09.jpg",
        "publicationDate": "19.12.16"
    },
    {
        "title": "108. 애매하면 죄가 된다",
        "url": "https://comic.naver.com/webtoon/detail?titleId=702608&no=108&week=tue",
        "imageUrl": "https://image-comic.pstatic.net/webtoon/702608/108/thumbnail_202x120_7facd4e6-4d14-4884-80a3-94b1f8c59854.jpg",
        "publicationDate": "19.12.09"
    },
    {
        "title": "107. 준우에게 다가가는 법2",
        "url": "https://comic.naver.com/webtoon/detail?titleId=702608&no=107&week=tue",
        "imageUrl": "https://image-comic.pstatic.net/webtoon/702608/107/thumbnail_202x120_0f809a5d-17d4-4985-b91c-b1f756f137a7.jpg",
        "publicationDate": "19.12.02"
    },
    {
        "title": "106. 준우에게 다가가는 법",
        "url": "https://comic.naver.com/webtoon/detail?titleId=702608&no=106&week=tue",
        "imageUrl": "https://image-comic.pstatic.net/webtoon/702608/106/thumbnail_202x120_9a7cdbf7-77fa-4c08-9a6c-570aa2c0d2bb.jpg",
        "publicationDate": "19.11.25"
    },
    {
        "title": "105. 종료",
        "url": "https://comic.naver.com/webtoon/detail?titleId=702608&no=105&week=tue",
        "imageUrl": "https://image-comic.pstatic.net/webtoon/702608/105/thumbnail_202x120_2e87d2eb-dcb2-4ed3-9dd3-1c62f6942e2e.jpg",
        "publicationDate": "19.11.18"
    },
    {
        "title": "104. 추격의 끝",
        "url": "https://comic.naver.com/webtoon/detail?titleId=702608&no=104&week=tue",
        "imageUrl": "https://image-comic.pstatic.net/webtoon/702608/104/thumbnail_202x120_ecafe7a3-4153-4a06-b9de-4790da61aec6.jpg",
        "publicationDate": "19.11.11"
    },
    {
        "title": "103. 우린 처음부터",
        "url": "https://comic.naver.com/webtoon/detail?titleId=702608&no=103&week=tue",
        "imageUrl": "https://image-comic.pstatic.net/webtoon/702608/103/thumbnail_202x120_0031e399-a25e-40aa-80ef-1e532844c15c.jpg",
        "publicationDate": "19.11.04"
    },
    {
        "title": "102. 좋아하거든",
        "url": "https://comic.naver.com/webtoon/detail?titleId=702608&no=102&week=tue",
        "imageUrl": "https://image-comic.pstatic.net/webtoon/702608/102/thumbnail_202x120_7fc815c7-ef5d-4572-99ca-40236fe41b8f.jpg",
        "publicationDate": "19.10.28"
    },
    {
        "title": "101. COUNT DOWN",
        "url": "https://comic.naver.com/webtoon/detail?titleId=702608&no=101&week=tue",
        "imageUrl": "https://image-comic.pstatic.net/webtoon/702608/101/thumbnail_202x120_c8022386-8667-4318-89b5-043a381faec6.jpg",
        "publicationDate": "19.10.21"
    },
    {
        "title": "100. 100화 특별편 + 100화 Heartbeat",
        "url": "https://comic.naver.com/webtoon/detail?titleId=702608&no=100&week=tue",
        "imageUrl": "https://image-comic.pstatic.net/webtoon/702608/100/thumbnail_202x120_932fd868-0050-4c14-99a0-fec3f03d7f33.jpg",
        "publicationDate": "19.10.14"
    },
    {
        "title": "99. Bravery (놀이공원 끝)",
        "url": "https://comic.naver.com/webtoon/detail?titleId=702608&no=99&week=tue",
        "imageUrl": "https://image-comic.pstatic.net/webtoon/702608/99/thumbnail_202x120_7ec33f3c-209f-4a23-8066-88636572dc02.jpg",
        "publicationDate": "19.10.07"
    },
    {
        "title": "98. 귀신의 집",
        "url": "https://comic.naver.com/webtoon/detail?titleId=702608&no=98&week=tue",
        "imageUrl": "https://image-comic.pstatic.net/webtoon/702608/98/thumbnail_202x120_ffad6dea-868a-44da-a37e-c5d1912dd52c.jpg",
        "publicationDate": "19.09.30"
    },
    {
        "title": "97. 타인은 천국이다",
        "url": "https://comic.naver.com/webtoon/detail?titleId=702608&no=97&week=tue",
        "imageUrl": "https://image-comic.pstatic.net/webtoon/702608/97/thumbnail_202x120_9bbf4da8-24b0-4f88-a014-6a234a6cc13e.jpg",
        "publicationDate": "19.09.23"
    },
    {
        "title": "96. 정상이 아니구나",
        "url": "https://comic.naver.com/webtoon/detail?titleId=702608&no=96&week=tue",
        "imageUrl": "https://image-comic.pstatic.net/webtoon/702608/96/thumbnail_202x120_811d7bc0-6518-44d5-83af-c25bbbb38fd2.jpg",
        "publicationDate": "19.09.16"
    },
    {
        "title": "95. go now",
        "url": "https://comic.naver.com/webtoon/detail?titleId=702608&no=95&week=tue",
        "imageUrl": "https://image-comic.pstatic.net/webtoon/702608/95/thumbnail_202x120_7b319437-9588-4903-b4fb-2211d1c729f2.jpg",
        "publicationDate": "19.09.09"
    },
    {
        "title": "94. 괜찮지가 않아",
        "url": "https://comic.naver.com/webtoon/detail?titleId=702608&no=94&week=tue",
        "imageUrl": "https://image-comic.pstatic.net/webtoon/702608/94/thumbnail_202x120_a0b59ccb-60cc-4b35-9953-3fa55a51e6de.jpg",
        "publicationDate": "19.09.02"
    },
    {
        "title": "93. 눈치게임",
        "url": "https://comic.naver.com/webtoon/detail?titleId=702608&no=93&week=tue",
        "imageUrl": "https://image-comic.pstatic.net/webtoon/702608/93/thumbnail_202x120_b0cb17c9-db3e-4905-8575-128e502c4227.jpg",
        "publicationDate": "19.08.26"
    },
    {
        "title": "92. 준비됐어?",
        "url": "https://comic.naver.com/webtoon/detail?titleId=702608&no=92&week=tue",
        "imageUrl": "https://image-comic.pstatic.net/webtoon/702608/92/thumbnail_202x120_d9ad6799-cd11-45e1-ad9b-1687b5e5cc86.jpg",
        "publicationDate": "19.08.19"
    },
    {
        "title": "91. 시작",
        "url": "https://comic.naver.com/webtoon/detail?titleId=702608&no=91&week=tue",
        "imageUrl": "https://image-comic.pstatic.net/webtoon/702608/91/thumbnail_202x120_c170e0e0-4beb-493b-b41d-3fcf7e0a757e.jpg",
        "publicationDate": "19.08.12"
    },
    {
        "title": "90. 끝",
        "url": "https://comic.naver.com/webtoon/detail?titleId=702608&no=90&week=tue",
        "imageUrl": "https://image-comic.pstatic.net/webtoon/702608/90/thumbnail_202x120_699fa6d7-3862-4752-86ad-e9360795f5ba.jpg",
        "publicationDate": "19.08.05"
    },
    {
        "title": "89. 진심이야",
        "url": "https://comic.naver.com/webtoon/detail?titleId=702608&no=89&week=tue",
        "imageUrl": "https://image-comic.pstatic.net/webtoon/702608/89/thumbnail_202x120_9fef731c-10e5-4ecd-8da6-1eb20fcc2fb3.jpg",
        "publicationDate": "19.07.29"
    },
    {
        "title": "88. 악당",
        "url": "https://comic.naver.com/webtoon/detail?titleId=702608&no=88&week=tue",
        "imageUrl": "https://image-comic.pstatic.net/webtoon/702608/88/thumbnail_202x120_ef756be8-1411-47b3-a43c-15cd8378f72e.jpg",
        "publicationDate": "19.07.22"
    },
    {
        "title": "87. 백설공주",
        "url": "https://comic.naver.com/webtoon/detail?titleId=702608&no=87&week=tue",
        "imageUrl": "https://image-comic.pstatic.net/webtoon/702608/87/thumbnail_202x120_ef9b44c8-6590-4993-86f5-1a6d14a079fd.jpg",
        "publicationDate": "19.07.15"
    },
    {
        "title": "86. 모르는 것",
        "url": "https://comic.naver.com/webtoon/detail?titleId=702608&no=86&week=tue",
        "imageUrl": "https://image-comic.pstatic.net/webtoon/702608/86/thumbnail_202x120_cf25435c-90e7-4e0a-81cd-81c4031998c3.jpg",
        "publicationDate": "19.07.08"
    },
    {
        "title": "85. Better off dead",
        "url": "https://comic.naver.com/webtoon/detail?titleId=702608&no=85&week=tue",
        "imageUrl": "https://image-comic.pstatic.net/webtoon/702608/85/thumbnail_202x120_7960c6ad-a706-40ca-938c-6f970919d1c8.jpg",
        "publicationDate": "19.07.01"
    },
    {
        "title": "84. conflict",
        "url": "https://comic.naver.com/webtoon/detail?titleId=702608&no=84&week=tue",
        "imageUrl": "https://image-comic.pstatic.net/webtoon/702608/84/thumbnail_202x120_3cadaedb-0194-4b8f-a38c-e687e11fa6ab.jpg",
        "publicationDate": "19.06.24"
    },
    {
        "title": "83. 자학",
        "url": "https://comic.naver.com/webtoon/detail?titleId=702608&no=83&week=tue",
        "imageUrl": "https://image-comic.pstatic.net/webtoon/702608/83/thumbnail_202x120_fd3dafc6-7647-43f9-8be3-fd5b0955eabc.jpg",
        "publicationDate": "19.06.17"
    },
    {
        "title": "82. 가까운 곳",
        "url": "https://comic.naver.com/webtoon/detail?titleId=702608&no=82&week=tue",
        "imageUrl": "https://image-comic.pstatic.net/webtoon/702608/82/optimized_thumbnail_202x120_9b5d60ed-eeae-4a52-877d-d5c729b80346.jpg",
        "publicationDate": "19.06.10"
    },
    {
        "title": "81. TRAP CARD",
        "url": "https://comic.naver.com/webtoon/detail?titleId=702608&no=81&week=tue",
        "imageUrl": "https://image-comic.pstatic.net/webtoon/702608/81/optimized_thumbnail_202x120_c3ea344c-92d1-4dff-acf0-546214486911.jpg",
        "publicationDate": "19.06.03"
    },
    {
        "title": "80. 체육대회",
        "url": "https://comic.naver.com/webtoon/detail?titleId=702608&no=80&week=tue",
        "imageUrl": "https://image-comic.pstatic.net/webtoon/702608/80/optimized_thumbnail_202x120_dae33305-3f5b-4682-9c55-c1899a492c8b.jpg",
        "publicationDate": "19.05.27"
    },
    {
        "title": "79. 어떡할래?",
        "url": "https://comic.naver.com/webtoon/detail?titleId=702608&no=79&week=tue",
        "imageUrl": "https://image-comic.pstatic.net/webtoon/702608/79/optimized_thumbnail_202x120_2a256e20-a975-4e46-a2ec-e48a9b39f004.jpg",
        "publicationDate": "19.05.20"
    },
    {
        "title": "78. Too late",
        "url": "https://comic.naver.com/webtoon/detail?titleId=702608&no=78&week=tue",
        "imageUrl": "https://image-comic.pstatic.net/webtoon/702608/78/optimized_thumbnail_202x120_efbe3fad-ef70-4a2c-95e1-e7d72646dda8.jpg",
        "publicationDate": "19.05.13"
    },
    {
        "title": "77. BANG",
        "url": "https://comic.naver.com/webtoon/detail?titleId=702608&no=77&week=tue",
        "imageUrl": "https://image-comic.pstatic.net/webtoon/702608/77/optimized_thumbnail_202x120_b4a11b3f-3827-46c2-ab9b-e8bc520975ad.jpg",
        "publicationDate": "19.05.06"
    },
    {
        "title": "76. 그림자",
        "url": "https://comic.naver.com/webtoon/detail?titleId=702608&no=76&week=tue",
        "imageUrl": "https://image-comic.pstatic.net/webtoon/702608/76/optimized_thumbnail_202x120_b58b8878-3619-4e14-a73f-f31266e440fb.jpg",
        "publicationDate": "19.04.29"
    },
    {
        "title": "75. 역전의 기회",
        "url": "https://comic.naver.com/webtoon/detail?titleId=702608&no=75&week=tue",
        "imageUrl": "https://image-comic.pstatic.net/webtoon/702608/75/optimized_thumbnail_202x120_f5a3f7c9-7406-4aaf-83cc-74b8e96cd9bd.jpg",
        "publicationDate": "19.04.22"
    },
    {
        "title": "74. 브레이크",
        "url": "https://comic.naver.com/webtoon/detail?titleId=702608&no=74&week=tue",
        "imageUrl": "https://image-comic.pstatic.net/webtoon/702608/74/optimized_thumbnail_202x120_2a287a6d-038b-4474-9470-bdfb9e20152e.jpg",
        "publicationDate": "19.04.15"
    },
    {
        "title": "73. 나의 친구를 위해",
        "url": "https://comic.naver.com/webtoon/detail?titleId=702608&no=73&week=tue",
        "imageUrl": "https://image-comic.pstatic.net/webtoon/702608/73/optimized_thumbnail_202x120_b56d77bd-f4c3-4195-897b-f014c41f35d8.jpg",
        "publicationDate": "19.04.08"
    },
    {
        "title": "72. motive",
        "url": "https://comic.naver.com/webtoon/detail?titleId=702608&no=72&week=tue",
        "imageUrl": "https://image-comic.pstatic.net/webtoon/702608/72/optimized_thumbnail_202x120_7910a530-64ee-453d-8a88-5e9bdd95bf5e.jpg",
        "publicationDate": "19.04.01"
    },
    {
        "title": "71. 너의 친구를 위해",
        "url": "https://comic.naver.com/webtoon/detail?titleId=702608&no=71&week=tue",
        "imageUrl": "https://image-comic.pstatic.net/webtoon/702608/71/optimized_thumbnail_202x120_9dcc0752-499f-4791-acb8-108aae0825c3.jpg",
        "publicationDate": "19.03.25"
    },
    {
        "title": "70. Opportunist",
        "url": "https://comic.naver.com/webtoon/detail?titleId=702608&no=70&week=tue",
        "imageUrl": "https://image-comic.pstatic.net/webtoon/702608/70/optimized_thumbnail_202x120_f11bea63-3b00-4d03-97a7-c50c27657b49.jpg",
        "publicationDate": "19.03.18"
    },
    {
        "title": "69. neutrality",
        "url": "https://comic.naver.com/webtoon/detail?titleId=702608&no=69&week=tue",
        "imageUrl": "https://image-comic.pstatic.net/webtoon/702608/69/optimized_thumbnail_202x120_e2b04330-8160-4e0f-8de5-ab21556dd181.jpg",
        "publicationDate": "19.03.11"
    },
    {
        "title": "68. 왜 하필",
        "url": "https://comic.naver.com/webtoon/detail?titleId=702608&no=68&week=tue",
        "imageUrl": "https://image-comic.pstatic.net/webtoon/702608/68/optimized_thumbnail_202x120_d95edb6b-6f6d-4bf2-a876-10e5126314ce.jpg",
        "publicationDate": "19.03.04"
    },
    {
        "title": "67. 나는 너를",
        "url": "https://comic.naver.com/webtoon/detail?titleId=702608&no=67&week=tue",
        "imageUrl": "https://image-comic.pstatic.net/webtoon/702608/67/optimized_thumbnail_202x120_051b158b-7de2-45fe-a708-458f7505f6ba.jpg",
        "publicationDate": "19.02.25"
    },
    {
        "title": "66. 기대감",
        "url": "https://comic.naver.com/webtoon/detail?titleId=702608&no=66&week=tue",
        "imageUrl": "https://image-comic.pstatic.net/webtoon/702608/66/optimized_thumbnail_202x120_58f5d2d0-3e55-4e38-94a5-762103599b11.jpg",
        "publicationDate": "19.02.18"
    },
    {
        "title": "65. HAPPY ENDING",
        "url": "https://comic.naver.com/webtoon/detail?titleId=702608&no=65&week=tue",
        "imageUrl": "https://image-comic.pstatic.net/webtoon/702608/65/optimized_thumbnail_202x120_4f4c160c-74cb-42bd-92f1-71bd184dccc9.jpg",
        "publicationDate": "19.02.11"
    },
    {
        "title": "64. 해결책",
        "url": "https://comic.naver.com/webtoon/detail?titleId=702608&no=64&week=tue",
        "imageUrl": "https://image-comic.pstatic.net/webtoon/702608/64/optimized_thumbnail_202x120_8ea584dc-0742-4281-9a7c-4197a514edc0.jpg",
        "publicationDate": "19.02.04"
    },
    {
        "title": "63. 역전",
        "url": "https://comic.naver.com/webtoon/detail?titleId=702608&no=63&week=tue",
        "imageUrl": "https://image-comic.pstatic.net/webtoon/702608/63/optimized_thumbnail_202x120_2654b438-0654-42aa-837a-fec43f43f5b7.jpg",
        "publicationDate": "19.01.28"
    },
    {
        "title": "62. 전세",
        "url": "https://comic.naver.com/webtoon/detail?titleId=702608&no=62&week=tue",
        "imageUrl": "https://image-comic.pstatic.net/webtoon/702608/62/optimized_thumbnail_202x120_0de1a9cd-c4f3-4f26-a13d-0f446c657c60.jpg",
        "publicationDate": "19.01.21"
    },
    {
        "title": "61. PUSHOVER",
        "url": "https://comic.naver.com/webtoon/detail?titleId=702608&no=61&week=tue",
        "imageUrl": "https://image-comic.pstatic.net/webtoon/702608/61/optimized_thumbnail_202x120_e77377c0-cf41-42a3-a589-3939d9ffccff.jpg",
        "publicationDate": "19.01.14"
    },
    {
        "title": "60. 폭풍",
        "url": "https://comic.naver.com/webtoon/detail?titleId=702608&no=60&week=tue",
        "imageUrl": "https://image-comic.pstatic.net/webtoon/702608/60/optimized_thumbnail_202x120_366048fe-8d1d-4aeb-a39b-3a9ef96129e3.jpg",
        "publicationDate": "19.01.07"
    },
    {
        "title": "59. 폭풍전야",
        "url": "https://comic.naver.com/webtoon/detail?titleId=702608&no=59&week=tue",
        "imageUrl": "https://image-comic.pstatic.net/webtoon/702608/59/optimized_thumbnail_202x120_ad7843fe-e5a0-49f0-842b-95d179b7c233.jpg",
        "publicationDate": "18.12.31"
    },
    {
        "title": "58. 재앙은 미묘하게",
        "url": "https://comic.naver.com/webtoon/detail?titleId=702608&no=58&week=tue",
        "imageUrl": "https://image-comic.pstatic.net/webtoon/702608/58/optimized_thumbnail_202x120_b4e08ad6-37c1-4edb-b92a-1a37bdfe23d0.jpg",
        "publicationDate": "18.12.24"
    },
    {
        "title": "57. 나아가다",
        "url": "https://comic.naver.com/webtoon/detail?titleId=702608&no=57&week=tue",
        "imageUrl": "https://image-comic.pstatic.net/webtoon/702608/57/optimized_thumbnail_202x120_25772df5-b1eb-4aa6-87ec-d429ca92bf94.jpg",
        "publicationDate": "18.12.17"
    },
    {
        "title": "56. 어떻게 생각해?",
        "url": "https://comic.naver.com/webtoon/detail?titleId=702608&no=56&week=tue",
        "imageUrl": "https://image-comic.pstatic.net/webtoon/702608/56/optimized_thumbnail_202x120_8b844d74-2a4d-4fbb-95f4-4a9bb88df65c.jpg",
        "publicationDate": "18.12.10"
    },
    {
        "title": "55. 시간의 끝에서",
        "url": "https://comic.naver.com/webtoon/detail?titleId=702608&no=55&week=tue",
        "imageUrl": "https://image-comic.pstatic.net/webtoon/702608/55/optimized_thumbnail_202x120_a1375aac-18b5-4a59-9c2e-46aa7048efb7.jpg",
        "publicationDate": "18.12.03"
    },
    {
        "title": "54. 의지",
        "url": "https://comic.naver.com/webtoon/detail?titleId=702608&no=54&week=tue",
        "imageUrl": "https://image-comic.pstatic.net/webtoon/702608/54/optimized_thumbnail_202x120_bcfc2051-5c41-48c6-80e5-24c33acca3b4.jpg",
        "publicationDate": "18.11.26"
    },
    {
        "title": "53. 딜레마",
        "url": "https://comic.naver.com/webtoon/detail?titleId=702608&no=53&week=tue",
        "imageUrl": "https://image-comic.pstatic.net/webtoon/702608/53/optimized_thumbnail_202x120_089538db-daac-4425-b505-b68db2c19b64.jpg",
        "publicationDate": "18.11.19"
    },
    {
        "title": "52. 네가 원하던 것",
        "url": "https://comic.naver.com/webtoon/detail?titleId=702608&no=52&week=tue",
        "imageUrl": "https://image-comic.pstatic.net/webtoon/702608/52/optimized_thumbnail_202x120_642cab48-e5ff-4913-8f01-1f6db6c72acf.jpg",
        "publicationDate": "18.11.12"
    },
    {
        "title": "51. 나랑 사귈래?",
        "url": "https://comic.naver.com/webtoon/detail?titleId=702608&no=51&week=tue",
        "imageUrl": "https://image-comic.pstatic.net/webtoon/702608/51/optimized_thumbnail_202x120_9263ae5d-dedb-4f13-a0d0-82e95c582e80.jpg",
        "publicationDate": "18.11.05"
    },
    {
        "title": "50. 청춘사연",
        "url": "https://comic.naver.com/webtoon/detail?titleId=702608&no=50&week=tue",
        "imageUrl": "https://image-comic.pstatic.net/webtoon/702608/50/optimized_thumbnail_202x120_67fc5eaf-9892-4e2d-bb87-7215bc3dd0f9.jpg",
        "publicationDate": "18.10.29"
    },
    {
        "title": "49. CHANGE",
        "url": "https://comic.naver.com/webtoon/detail?titleId=702608&no=49&week=tue",
        "imageUrl": "https://image-comic.pstatic.net/webtoon/702608/49/optimized_thumbnail_202x120_d93533fc-ff47-4035-9ddf-eac0cb6993be.jpg",
        "publicationDate": "18.10.15"
    },
    {
        "title": "48. GET OVER",
        "url": "https://comic.naver.com/webtoon/detail?titleId=702608&no=48&week=tue",
        "imageUrl": "https://image-comic.pstatic.net/webtoon/702608/48/optimized_thumbnail_202x120_a59bd19a-05c1-4a49-8699-1df6053f3b07.jpg",
        "publicationDate": "18.10.08"
    },
    {
        "title": "47. RE:",
        "url": "https://comic.naver.com/webtoon/detail?titleId=702608&no=47&week=tue",
        "imageUrl": "https://image-comic.pstatic.net/webtoon/702608/47/optimized_thumbnail_202x120_7f81d3ca-d7ef-4e75-99ac-92a2cf6f8cd6.jpg",
        "publicationDate": "18.10.01"
    },
    {
        "title": "46. 미안해",
        "url": "https://comic.naver.com/webtoon/detail?titleId=702608&no=46&week=tue",
        "imageUrl": "https://image-comic.pstatic.net/webtoon/702608/46/optimized_thumbnail_202x120_0a887dfc-87ce-4377-90cb-0161abfc2045.jpg",
        "publicationDate": "18.09.24"
    },
    {
        "title": "45. NUMB",
        "url": "https://comic.naver.com/webtoon/detail?titleId=702608&no=45&week=tue",
        "imageUrl": "https://image-comic.pstatic.net/webtoon/702608/45/optimized_thumbnail_202x120_3fefbd65-d440-48df-b4c8-1166323ee7a4.jpg",
        "publicationDate": "18.09.17"
    },
    {
        "title": "44. 마음",
        "url": "https://comic.naver.com/webtoon/detail?titleId=702608&no=44&week=tue",
        "imageUrl": "https://image-comic.pstatic.net/webtoon/702608/44/optimized_thumbnail_202x120_b813c385-1ba3-438e-9c8b-26fbdf71ee49.jpg",
        "publicationDate": "18.09.10"
    },
    {
        "title": "43. 아이스박스",
        "url": "https://comic.naver.com/webtoon/detail?titleId=702608&no=43&week=tue",
        "imageUrl": "https://image-comic.pstatic.net/webtoon/702608/43/optimized_thumbnail_202x120_d5ffe63a-7e2a-4867-b2cf-27208320b3ea.jpg",
        "publicationDate": "18.09.03"
    },
    {
        "title": "42. 착각",
        "url": "https://comic.naver.com/webtoon/detail?titleId=702608&no=42&week=tue",
        "imageUrl": "https://image-comic.pstatic.net/webtoon/702608/42/optimized_thumbnail_202x120_088f3626-9c32-42dc-8f6e-88f2d3b0e6f4.jpg",
        "publicationDate": "18.08.27"
    },
    {
        "title": "41. 인사이드 아웃",
        "url": "https://comic.naver.com/webtoon/detail?titleId=702608&no=41&week=tue",
        "imageUrl": "https://image-comic.pstatic.net/webtoon/702608/41/optimized_thumbnail_202x120_b16b8fbd-c297-479b-83e4-b1d4ab3dbea3.jpg",
        "publicationDate": "18.08.20"
    },
    {
        "title": "40. GET READY",
        "url": "https://comic.naver.com/webtoon/detail?titleId=702608&no=40&week=tue",
        "imageUrl": "https://image-comic.pstatic.net/webtoon/702608/40/optimized_thumbnail_202x120_59af598c-40fd-47bc-9834-02e5d7890d37.jpg",
        "publicationDate": "18.08.13"
    },
    {
        "title": "39. 너보다",
        "url": "https://comic.naver.com/webtoon/detail?titleId=702608&no=39&week=tue",
        "imageUrl": "https://image-comic.pstatic.net/webtoon/702608/39/optimized_thumbnail_202x120_39f01627-6801-44a5-a70c-2c99780f35e0.jpg",
        "publicationDate": "18.08.06"
    },
    {
        "title": "38. The Last Man Standing",
        "url": "https://comic.naver.com/webtoon/detail?titleId=702608&no=38&week=tue",
        "imageUrl": "https://image-comic.pstatic.net/webtoon/702608/38/optimized_thumbnail_202x120_25390d78-cf96-4414-a6c0-6a20b689c028.jpg",
        "publicationDate": "18.07.30"
    },
    {
        "title": "37. 교차",
        "url": "https://comic.naver.com/webtoon/detail?titleId=702608&no=37&week=tue",
        "imageUrl": "https://image-comic.pstatic.net/webtoon/702608/37/optimized_thumbnail_202x120_69092ea6-d17d-479f-8e8f-b8ca407e2773.jpg",
        "publicationDate": "18.07.23"
    },
    {
        "title": "36. Revenge",
        "url": "https://comic.naver.com/webtoon/detail?titleId=702608&no=36&week=tue",
        "imageUrl": "https://image-comic.pstatic.net/webtoon/702608/36/optimized_thumbnail_202x120_5d44f603-59ba-4a5f-8455-f55d9eb117db.jpg",
        "publicationDate": "18.07.16"
    },
    {
        "title": "35. U Go Girl",
        "url": "https://comic.naver.com/webtoon/detail?titleId=702608&no=35&week=tue",
        "imageUrl": "https://image-comic.pstatic.net/webtoon/702608/35/optimized_thumbnail_202x120_5cf8a126-52e4-45e9-8178-9b6a04ad67aa.jpg",
        "publicationDate": "18.07.09"
    },
    {
        "title": "34. Twilight",
        "url": "https://comic.naver.com/webtoon/detail?titleId=702608&no=34&week=tue",
        "imageUrl": "https://image-comic.pstatic.net/webtoon/702608/34/optimized_thumbnail_202x120_21ad5639-18ea-473f-b5ac-f980eee574fe.jpg",
        "publicationDate": "18.07.02"
    },
    {
        "title": "33. 내 알 바냐?",
        "url": "https://comic.naver.com/webtoon/detail?titleId=702608&no=33&week=tue",
        "imageUrl": "https://image-comic.pstatic.net/webtoon/702608/33/optimized_thumbnail_202x120_461cfcda-6e01-4cb4-b0dc-26989583abe4.jpg",
        "publicationDate": "18.06.25"
    },
    {
        "title": "32. 거인",
        "url": "https://comic.naver.com/webtoon/detail?titleId=702608&no=32&week=tue",
        "imageUrl": "https://image-comic.pstatic.net/webtoon/702608/32/optimized_thumbnail_202x120_8125e396-57fd-4901-b282-0ee6afd8a8b7.jpg",
        "publicationDate": "18.06.18"
    },
    {
        "title": "31. Suddenly",
        "url": "https://comic.naver.com/webtoon/detail?titleId=702608&no=31&week=tue",
        "imageUrl": "https://image-comic.pstatic.net/webtoon/702608/31/optimized_thumbnail_202x120_75351456-0abc-4ed9-98eb-6e52dbe9102e.jpg",
        "publicationDate": "18.06.11"
    },
    {
        "title": "30. 경고",
        "url": "https://comic.naver.com/webtoon/detail?titleId=702608&no=30&week=tue",
        "imageUrl": "https://image-comic.pstatic.net/webtoon/702608/30/optimized_thumbnail_202x120_154716dc-f3b0-4a0a-8d5a-a1027c430618.jpg",
        "publicationDate": "18.06.04"
    },
    {
        "title": "29. 영원한 비밀은 없다.",
        "url": "https://comic.naver.com/webtoon/detail?titleId=702608&no=29&week=tue",
        "imageUrl": "https://image-comic.pstatic.net/webtoon/702608/29/optimized_thumbnail_202x120_474f69bc-b882-4ef7-a7ee-39dc7dba1208.jpg",
        "publicationDate": "18.05.28"
    },
    {
        "title": "28. 앞을 봐",
        "url": "https://comic.naver.com/webtoon/detail?titleId=702608&no=28&week=tue",
        "imageUrl": "https://image-comic.pstatic.net/webtoon/702608/28/optimized_thumbnail_202x120_233a0221-73a6-4e83-bab6-d48a64b260bf.jpg",
        "publicationDate": "18.05.21"
    },
    {
        "title": "27. 관계",
        "url": "https://comic.naver.com/webtoon/detail?titleId=702608&no=27&week=tue",
        "imageUrl": "https://image-comic.pstatic.net/webtoon/702608/27/optimized_thumbnail_202x120_d07f908c-a013-4182-aa81-6baf8bae2ed7.jpg",
        "publicationDate": "18.05.14"
    },
    {
        "title": "26. 내가 준우는 아니니까",
        "url": "https://comic.naver.com/webtoon/detail?titleId=702608&no=26&week=tue",
        "imageUrl": "https://image-comic.pstatic.net/webtoon/702608/26/optimized_thumbnail_202x120_a7bcf130-fea5-45b0-ad3f-6645357a2c0c.jpg",
        "publicationDate": "18.05.07"
    },
    {
        "title": "25. 확실한 한가지",
        "url": "https://comic.naver.com/webtoon/detail?titleId=702608&no=25&week=tue",
        "imageUrl": "https://image-comic.pstatic.net/webtoon/702608/25/optimized_thumbnail_202x120_937cc66e-2f03-4354-a7d5-cf53372616b1.jpg",
        "publicationDate": "18.04.30"
    },
    {
        "title": "24. IN THE END",
        "url": "https://comic.naver.com/webtoon/detail?titleId=702608&no=24&week=tue",
        "imageUrl": "https://image-comic.pstatic.net/webtoon/702608/24/optimized_thumbnail_202x120_cc12e141-0285-4316-97be-f75f8814b63f.jpg",
        "publicationDate": "18.04.23"
    },
    {
        "title": "23. 기억의 끝",
        "url": "https://comic.naver.com/webtoon/detail?titleId=702608&no=23&week=tue",
        "imageUrl": "https://image-comic.pstatic.net/webtoon/702608/23/optimized_thumbnail_202x120_5993c101-d7f7-4efe-8082-e96f3bc28a1a.jpg",
        "publicationDate": "18.04.16"
    },
    {
        "title": "22. 백색왜성",
        "url": "https://comic.naver.com/webtoon/detail?titleId=702608&no=22&week=tue",
        "imageUrl": "https://image-comic.pstatic.net/webtoon/702608/22/optimized_thumbnail_202x120_a6f8b40c-df9c-4fc7-98e2-423776e6feb8.jpg",
        "publicationDate": "18.04.09"
    },
    {
        "title": "21. 기억을 걷는 시간",
        "url": "https://comic.naver.com/webtoon/detail?titleId=702608&no=21&week=tue",
        "imageUrl": "https://image-comic.pstatic.net/webtoon/702608/21/optimized_thumbnail_202x120_a7320912-def0-4cc2-8421-2dd63f391301.jpg",
        "publicationDate": "18.04.02"
    },
    {
        "title": "20. 무슨 일이 있었던 거야?",
        "url": "https://comic.naver.com/webtoon/detail?titleId=702608&no=20&week=tue",
        "imageUrl": "https://image-comic.pstatic.net/webtoon/702608/20/optimized_thumbnail_202x120_edc8a74d-f7dd-4243-a60a-5631aa8574e5.jpg",
        "publicationDate": "18.03.26"
    },
    {
        "title": "19. 기억났다",
        "url": "https://comic.naver.com/webtoon/detail?titleId=702608&no=19&week=tue",
        "imageUrl": "https://image-comic.pstatic.net/webtoon/702608/19/optimized_thumbnail_202x120_18ed0f15-01c5-470c-8c97-38013ee30187.jpg",
        "publicationDate": "18.03.19"
    },
    {
        "title": "18. 관심없어",
        "url": "https://comic.naver.com/webtoon/detail?titleId=702608&no=18&week=tue",
        "imageUrl": "https://image-comic.pstatic.net/webtoon/702608/18/optimized_thumbnail_202x120_d35b7bb0-d3a4-4de4-b5e7-4ded3cc3d8e1.jpg",
        "publicationDate": "18.03.12"
    },
    {
        "title": "17. 있잖아",
        "url": "https://comic.naver.com/webtoon/detail?titleId=702608&no=17&week=tue",
        "imageUrl": "https://image-comic.pstatic.net/webtoon/702608/17/optimized_thumbnail_202x120_51ddf2fb-4fc6-4ac8-a664-106f1624797a.jpg",
        "publicationDate": "18.03.05"
    },
    {
        "title": "16. 총알 피하기",
        "url": "https://comic.naver.com/webtoon/detail?titleId=702608&no=16&week=tue",
        "imageUrl": "https://image-comic.pstatic.net/webtoon/702608/16/optimized_thumbnail_202x120_02033a9c-7c75-47f6-acf7-1c442c395b02.jpg",
        "publicationDate": "18.02.26"
    },
    {
        "title": "15. 말 한마디",
        "url": "https://comic.naver.com/webtoon/detail?titleId=702608&no=15&week=tue",
        "imageUrl": "https://image-comic.pstatic.net/webtoon/702608/15/optimized_thumbnail_202x120_d8589907-c44f-4cb4-883c-909e635bd84e.jpg",
        "publicationDate": "18.02.19"
    },
    {
        "title": "14. 힝 속았지?",
        "url": "https://comic.naver.com/webtoon/detail?titleId=702608&no=14&week=tue",
        "imageUrl": "https://image-comic.pstatic.net/webtoon/702608/14/optimized_thumbnail_202x120_a13d87cd-0e38-41c5-8fa1-3ac71965d88f.jpg",
        "publicationDate": "18.02.12"
    },
    {
        "title": "13. EXTRA",
        "url": "https://comic.naver.com/webtoon/detail?titleId=702608&no=13&week=tue",
        "imageUrl": "https://image-comic.pstatic.net/webtoon/702608/13/optimized_thumbnail_202x120_61bd1cb7-febd-40f9-b0b4-e25837cd71b1.jpg",
        "publicationDate": "18.02.05"
    },
    {
        "title": "12. 내가 해줄 수 있는것",
        "url": "https://comic.naver.com/webtoon/detail?titleId=702608&no=12&week=tue",
        "imageUrl": "https://image-comic.pstatic.net/webtoon/702608/12/optimized_thumbnail_202x120_b91d5df6-4c37-466c-bcc5-a13ce178c828.jpg",
        "publicationDate": "18.01.29"
    },
    {
        "title": "11. 처음부터",
        "url": "https://comic.naver.com/webtoon/detail?titleId=702608&no=11&week=tue",
        "imageUrl": "https://image-comic.pstatic.net/webtoon/702608/11/optimized_thumbnail_202x120_eaa375a8-531e-4e55-9e9c-ecce32c2c4f8.jpg",
        "publicationDate": "18.01.22"
    },
    {
        "title": "10. 잠깐만",
        "url": "https://comic.naver.com/webtoon/detail?titleId=702608&no=10&week=tue",
        "imageUrl": "https://image-comic.pstatic.net/webtoon/702608/10/optimized_thumbnail_202x120_f6e35e0c-f0fe-4859-88bb-d37bb94a2475.jpg",
        "publicationDate": "18.01.15"
    },
    {
        "title": "9. 추적",
        "url": "https://comic.naver.com/webtoon/detail?titleId=702608&no=9&week=tue",
        "imageUrl": "https://image-comic.pstatic.net/webtoon/702608/9/optimized_thumbnail_202x120_b1dad18e-f522-4e6e-b92b-89de3f1505b2.jpg",
        "publicationDate": "18.01.08"
    },
    {
        "title": "8. 정체",
        "url": "https://comic.naver.com/webtoon/detail?titleId=702608&no=8&week=tue",
        "imageUrl": "https://image-comic.pstatic.net/webtoon/702608/8/optimized_thumbnail_202x120_b85f080e-a796-4bfe-a07a-628e7a7dfe1b.jpg",
        "publicationDate": "18.01.01"
    },
    {
        "title": "7. 준비",
        "url": "https://comic.naver.com/webtoon/detail?titleId=702608&no=7&week=tue",
        "imageUrl": "https://image-comic.pstatic.net/webtoon/702608/7/optimized_thumbnail_202x120_10f1a754-84ce-4053-9388-64644f50edb2.jpg",
        "publicationDate": "17.12.25"
    },
    {
        "title": "6. 동아리 첫 날",
        "url": "https://comic.naver.com/webtoon/detail?titleId=702608&no=6&week=tue",
        "imageUrl": "https://image-comic.pstatic.net/webtoon/702608/6/optimized_thumbnail_202x120_d33cda48-1cf3-4b4d-99c3-4c5cabe8da5d.jpg",
        "publicationDate": "17.12.18"
    },
    {
        "title": "5. pc방에서 생긴일",
        "url": "https://comic.naver.com/webtoon/detail?titleId=702608&no=5&week=tue",
        "imageUrl": "https://image-comic.pstatic.net/webtoon/702608/5/optimized_thumbnail_202x120_5df0ef29-beae-4025-be1a-9d0d43285fdb.jpg",
        "publicationDate": "17.12.11"
    },
    {
        "title": "4. 될 수 없을까?",
        "url": "https://comic.naver.com/webtoon/detail?titleId=702608&no=4&week=tue",
        "imageUrl": "https://image-comic.pstatic.net/webtoon/702608/4/optimized_thumbnail_202x120_daa7f9d2-3f1f-4254-93eb-01df6b670902.jpg",
        "publicationDate": "17.12.04"
    },
    {
        "title": "3. 그녀의변화",
        "url": "https://comic.naver.com/webtoon/detail?titleId=702608&no=3&week=tue",
        "imageUrl": "https://image-comic.pstatic.net/webtoon/702608/3/optimized_thumbnail_202x120_1ef6e031-6455-400a-a47b-be08a50fdc20.jpg",
        "publicationDate": "17.11.27"
    },
    {
        "title": "2. 그녀의 이유",
        "url": "https://comic.naver.com/webtoon/detail?titleId=702608&no=2&week=tue",
        "imageUrl": "https://image-comic.pstatic.net/webtoon/702608/2/optimized_thumbnail_202x120_b81b89f7-2608-4ba3-bace-8551d67cf1b3.jpg",
        "publicationDate": "17.11.20"
    },
    {
        "title": "1. 우연",
        "url": "https://comic.naver.com/webtoon/detail?titleId=702608&no=1&week=tue",
        "imageUrl": "https://image-comic.pstatic.net/webtoon/702608/1/optimized_thumbnail_202x120_805cd7ee-b373-4530-a64d-930049ed007a.jpg",
        "publicationDate": "17.11.13"
    }
]