[
    {
        "title": "48화",
        "url": "https://comic.naver.com/webtoon/detail?titleId=803649&no=48&week=sun",
        "imageUrl": "https://image-comic.pstatic.net/webtoon/803649/48/thumbnail_202x120_dd9cbd5a-cad3-4050-b00d-8768bfdb85de.jpg",
        "publicationDate": "23.11.18"
    },
    {
        "title": "47화",
        "url": "https://comic.naver.com/webtoon/detail?titleId=803649&no=47&week=sun",
        "imageUrl": "https://image-comic.pstatic.net/webtoon/803649/47/thumbnail_202x120_9379fd02-16d7-4dcb-a2fa-784bade592e0.jpg",
        "publicationDate": "23.11.11"
    },
    {
        "title": "46화",
        "url": "https://comic.naver.com/webtoon/detail?titleId=803649&no=46&week=sun",
        "imageUrl": "https://image-comic.pstatic.net/webtoon/803649/46/thumbnail_202x120_93c8fad4-d80a-4b6c-821e-e867e1047d15.jpg",
        "publicationDate": "23.11.04"
    },
    {
        "title": "45화",
        "url": "https://comic.naver.com/webtoon/detail?titleId=803649&no=45&week=sun",
        "imageUrl": "https://image-comic.pstatic.net/webtoon/803649/45/thumbnail_202x120_cf9a57c2-5c76-4084-bc85-fd7c6b6d4824.jpg",
        "publicationDate": "23.10.28"
    },
    {
        "title": "44화",
        "url": "https://comic.naver.com/webtoon/detail?titleId=803649&no=44&week=sun",
        "imageUrl": "https://image-comic.pstatic.net/webtoon/803649/44/thumbnail_202x120_1ab52aba-dcf5-4eef-80de-30b78f2cef04.jpg",
        "publicationDate": "23.10.21"
    },
    {
        "title": "43화",
        "url": "https://comic.naver.com/webtoon/detail?titleId=803649&no=43&week=sun",
        "imageUrl": "https://image-comic.pstatic.net/webtoon/803649/43/thumbnail_202x120_74f943fd-030d-4061-bda6-df572720f043.jpg",
        "publicationDate": "23.10.14"
    },
    {
        "title": "42화",
        "url": "https://comic.naver.com/webtoon/detail?titleId=803649&no=42&week=sun",
        "imageUrl": "https://image-comic.pstatic.net/webtoon/803649/42/thumbnail_202x120_25c71b1a-4254-4b55-9002-d8ba2a9a3b52.jpg",
        "publicationDate": "23.10.07"
    },
    {
        "title": "41화",
        "url": "https://comic.naver.com/webtoon/detail?titleId=803649&no=41&week=sun",
        "imageUrl": "https://image-comic.pstatic.net/webtoon/803649/41/thumbnail_202x120_e4c3b851-b923-4664-8da5-02d72953717c.jpg",
        "publicationDate": "23.09.30"
    },
    {
        "title": "40화",
        "url": "https://comic.naver.com/webtoon/detail?titleId=803649&no=40&week=sun",
        "imageUrl": "https://image-comic.pstatic.net/webtoon/803649/40/thumbnail_202x120_3d892aec-33e0-46cf-9069-19f2766f380a.jpg",
        "publicationDate": "23.09.23"
    },
    {
        "title": "39화",
        "url": "https://comic.naver.com/webtoon/detail?titleId=803649&no=39&week=sun",
        "imageUrl": "https://image-comic.pstatic.net/webtoon/803649/39/thumbnail_202x120_cd9634d2-aa8c-4087-8dba-bacfe5eeccdb.jpg",
        "publicationDate": "23.09.16"
    },
    {
        "title": "38화",
        "url": "https://comic.naver.com/webtoon/detail?titleId=803649&no=38&week=sun",
        "imageUrl": "https://image-comic.pstatic.net/webtoon/803649/38/thumbnail_202x120_0dfb3b17-4e3a-4cc7-bd68-d0c581a01adb.jpg",
        "publicationDate": "23.09.09"
    },
    {
        "title": "37화",
        "url": "https://comic.naver.com/webtoon/detail?titleId=803649&no=37&week=sun",
        "imageUrl": "https://image-comic.pstatic.net/webtoon/803649/37/thumbnail_202x120_bff43737-4869-4231-b372-7b376dcafb8c.jpg",
        "publicationDate": "23.09.02"
    },
    {
        "title": "36화",
        "url": "https://comic.naver.com/webtoon/detail?titleId=803649&no=36&week=sun",
        "imageUrl": "https://image-comic.pstatic.net/webtoon/803649/36/thumbnail_202x120_7a5ecb05-25d2-4a8e-b91a-1f289d0a4067.jpg",
        "publicationDate": "23.08.26"
    },
    {
        "title": "35화",
        "url": "https://comic.naver.com/webtoon/detail?titleId=803649&no=35&week=sun",
        "imageUrl": "https://image-comic.pstatic.net/webtoon/803649/35/thumbnail_202x120_83a0730f-dfcf-4054-accb-937c9f98dca3.jpg",
        "publicationDate": "23.08.19"
    },
    {
        "title": "34화",
        "url": "https://comic.naver.com/webtoon/detail?titleId=803649&no=34&week=sun",
        "imageUrl": "https://image-comic.pstatic.net/webtoon/803649/34/thumbnail_202x120_45ed6cc1-4e95-4a9f-9050-79ec3248c49e.jpg",
        "publicationDate": "23.08.12"
    },
    {
        "title": "33화",
        "url": "https://comic.naver.com/webtoon/detail?titleId=803649&no=33&week=sun",
        "imageUrl": "https://image-comic.pstatic.net/webtoon/803649/33/thumbnail_202x120_551232c7-375e-42da-a4e8-7de282c61b61.jpg",
        "publicationDate": "23.08.05"
    },
    {
        "title": "32화",
        "url": "https://comic.naver.com/webtoon/detail?titleId=803649&no=32&week=sun",
        "imageUrl": "https://image-comic.pstatic.net/webtoon/803649/32/thumbnail_202x120_4de9dd16-088f-471e-9394-b4eb831203b6.jpg",
        "publicationDate": "23.07.29"
    },
    {
        "title": "31화",
        "url": "https://comic.naver.com/webtoon/detail?titleId=803649&no=31&week=sun",
        "imageUrl": "https://image-comic.pstatic.net/webtoon/803649/31/thumbnail_202x120_7af4f2d4-d05c-4636-b592-325a8ab59544.jpg",
        "publicationDate": "23.07.15"
    },
    {
        "title": "30화",
        "url": "https://comic.naver.com/webtoon/detail?titleId=803649&no=30&week=sun",
        "imageUrl": "https://image-comic.pstatic.net/webtoon/803649/30/thumbnail_202x120_3ee4a7f6-debd-47bd-aaab-725073d30252.jpg",
        "publicationDate": "23.07.08"
    },
    {
        "title": "29화",
        "url": "https://comic.naver.com/webtoon/detail?titleId=803649&no=29&week=sun",
        "imageUrl": "https://image-comic.pstatic.net/webtoon/803649/29/thumbnail_202x120_5e90b52c-9d62-4493-a0b6-c6dd1a8634b9.jpg",
        "publicationDate": "23.07.01"
    },
    {
        "title": "28화",
        "url": "https://comic.naver.com/webtoon/detail?titleId=803649&no=28&week=sun",
        "imageUrl": "https://image-comic.pstatic.net/webtoon/803649/28/thumbnail_202x120_a2f3af7d-df48-445a-a709-6e214652305a.jpg",
        "publicationDate": "23.06.24"
    },
    {
        "title": "27화",
        "url": "https://comic.naver.com/webtoon/detail?titleId=803649&no=27&week=sun",
        "imageUrl": "https://image-comic.pstatic.net/webtoon/803649/27/thumbnail_202x120_17742d87-52c0-43a3-b600-05414719c83f.jpg",
        "publicationDate": "23.06.17"
    },
    {
        "title": "26화",
        "url": "https://comic.naver.com/webtoon/detail?titleId=803649&no=26&week=sun",
        "imageUrl": "https://image-comic.pstatic.net/webtoon/803649/26/thumbnail_202x120_a68c5a58-2109-4398-8b25-bdbd136ea63c.jpg",
        "publicationDate": "23.06.10"
    },
    {
        "title": "25화",
        "url": "https://comic.naver.com/webtoon/detail?titleId=803649&no=25&week=sun",
        "imageUrl": "https://image-comic.pstatic.net/webtoon/803649/25/thumbnail_202x120_0a9a60d0-2b8e-4468-8497-d3dc1b1e57b3.jpg",
        "publicationDate": "23.06.03"
    },
    {
        "title": "24화",
        "url": "https://comic.naver.com/webtoon/detail?titleId=803649&no=24&week=sun",
        "imageUrl": "https://image-comic.pstatic.net/webtoon/803649/24/thumbnail_202x120_db84c9a2-3cb7-48d1-ba57-8c0bb51c8cd8.jpg",
        "publicationDate": "23.05.27"
    },
    {
        "title": "23화",
        "url": "https://comic.naver.com/webtoon/detail?titleId=803649&no=23&week=sun",
        "imageUrl": "https://image-comic.pstatic.net/webtoon/803649/23/thumbnail_202x120_ea066fb4-0a93-4aab-80a0-bc13ffc34496.jpg",
        "publicationDate": "23.05.20"
    },
    {
        "title": "22화",
        "url": "https://comic.naver.com/webtoon/detail?titleId=803649&no=22&week=sun",
        "imageUrl": "https://image-comic.pstatic.net/webtoon/803649/22/thumbnail_202x120_7a336adb-9643-472a-9f88-28733eff7aab.jpg",
        "publicationDate": "23.05.13"
    },
    {
        "title": "21화",
        "url": "https://comic.naver.com/webtoon/detail?titleId=803649&no=21&week=sun",
        "imageUrl": "https://image-comic.pstatic.net/webtoon/803649/21/thumbnail_202x120_c7186952-1d2f-4a6e-91be-b0134330406c.jpg",
        "publicationDate": "23.05.06"
    },
    {
        "title": "20화",
        "url": "https://comic.naver.com/webtoon/detail?titleId=803649&no=20&week=sun",
        "imageUrl": "https://image-comic.pstatic.net/webtoon/803649/20/thumbnail_202x120_7daa99b1-3b7b-4041-9329-f06f72365603.jpg",
        "publicationDate": "23.04.29"
    },
    {
        "title": "19화",
        "url": "https://comic.naver.com/webtoon/detail?titleId=803649&no=19&week=sun",
        "imageUrl": "https://image-comic.pstatic.net/webtoon/803649/19/thumbnail_202x120_704e1a38-7dd7-451f-b02b-1a3471066688.jpg",
        "publicationDate": "23.04.22"
    },
    {
        "title": "18화",
        "url": "https://comic.naver.com/webtoon/detail?titleId=803649&no=18&week=sun",
        "imageUrl": "https://image-comic.pstatic.net/webtoon/803649/18/thumbnail_202x120_581b37e6-2ccd-4e31-89b7-47e7f0270138.jpg",
        "publicationDate": "23.04.15"
    },
    {
        "title": "17화",
        "url": "https://comic.naver.com/webtoon/detail?titleId=803649&no=17&week=sun",
        "imageUrl": "https://image-comic.pstatic.net/webtoon/803649/17/thumbnail_202x120_e6a7603e-eef4-4089-9064-eb858c16f489.jpg",
        "publicationDate": "23.04.08"
    },
    {
        "title": "16화",
        "url": "https://comic.naver.com/webtoon/detail?titleId=803649&no=16&week=sun",
        "imageUrl": "https://image-comic.pstatic.net/webtoon/803649/16/thumbnail_202x120_3f516cea-d648-4d8e-9251-a1aa50684168.jpg",
        "publicationDate": "23.04.01"
    },
    {
        "title": "15화",
        "url": "https://comic.naver.com/webtoon/detail?titleId=803649&no=15&week=sun",
        "imageUrl": "https://image-comic.pstatic.net/webtoon/803649/15/thumbnail_202x120_5087bf5a-61da-4ff8-8673-ddd91c875c0f.jpg",
        "publicationDate": "23.03.25"
    },
    {
        "title": "14화",
        "url": "https://comic.naver.com/webtoon/detail?titleId=803649&no=14&week=sun",
        "imageUrl": "https://image-comic.pstatic.net/webtoon/803649/14/thumbnail_202x120_d7dd33c0-c7c4-4c54-bfaf-584dad05f011.jpg",
        "publicationDate": "23.03.18"
    },
    {
        "title": "13화",
        "url": "https://comic.naver.com/webtoon/detail?titleId=803649&no=13&week=sun",
        "imageUrl": "https://image-comic.pstatic.net/webtoon/803649/13/thumbnail_202x120_3a96b2ec-9b00-4e94-ab7c-d3f36165bb05.jpg",
        "publicationDate": "23.03.11"
    },
    {
        "title": "12화",
        "url": "https://comic.naver.com/webtoon/detail?titleId=803649&no=12&week=sun",
        "imageUrl": "https://image-comic.pstatic.net/webtoon/803649/12/thumbnail_202x120_2c324281-d4a4-4a9e-83c7-e407fbd1fb34.jpg",
        "publicationDate": "23.03.04"
    },
    {
        "title": "11화",
        "url": "https://comic.naver.com/webtoon/detail?titleId=803649&no=11&week=sun",
        "imageUrl": "https://image-comic.pstatic.net/webtoon/803649/11/thumbnail_202x120_fc67d81f-c8b9-4054-be4d-df79721ba100.jpg",
        "publicationDate": "23.02.25"
    },
    {
        "title": "10화",
        "url": "https://comic.naver.com/webtoon/detail?titleId=803649&no=10&week=sun",
        "imageUrl": "https://image-comic.pstatic.net/webtoon/803649/10/thumbnail_202x120_bf46d9fc-2208-4f5c-8480-dfd9b290a444.jpg",
        "publicationDate": "23.02.18"
    },
    {
        "title": "9화",
        "url": "https://comic.naver.com/webtoon/detail?titleId=803649&no=9&week=sun",
        "imageUrl": "https://image-comic.pstatic.net/webtoon/803649/9/thumbnail_202x120_bbc56627-3c59-47ac-a41f-20e581f19ee4.jpg",
        "publicationDate": "23.02.11"
    },
    {
        "title": "8화",
        "url": "https://comic.naver.com/webtoon/detail?titleId=803649&no=8&week=sun",
        "imageUrl": "https://image-comic.pstatic.net/webtoon/803649/8/thumbnail_202x120_06e3f15d-c111-4cb4-a48e-d25402f0ddee.jpg",
        "publicationDate": "23.02.04"
    },
    {
        "title": "7화",
        "url": "https://comic.naver.com/webtoon/detail?titleId=803649&no=7&week=sun",
        "imageUrl": "https://image-comic.pstatic.net/webtoon/803649/7/thumbnail_202x120_50d667ea-9a2d-4293-a547-90d78f2bbfbe.jpg",
        "publicationDate": "23.01.28"
    },
    {
        "title": "6화",
        "url": "https://comic.naver.com/webtoon/detail?titleId=803649&no=6&week=sun",
        "imageUrl": "https://image-comic.pstatic.net/webtoon/803649/6/thumbnail_202x120_687371b9-3e10-4cf5-8625-22eb37208bff.jpg",
        "publicationDate": "23.01.21"
    },
    {
        "title": "5화",
        "url": "https://comic.naver.com/webtoon/detail?titleId=803649&no=5&week=sun",
        "imageUrl": "https://image-comic.pstatic.net/webtoon/803649/5/thumbnail_202x120_714550ac-6523-405c-9f82-494804887f5e.jpg",
        "publicationDate": "23.01.14"
    },
    {
        "title": "4화",
        "url": "https://comic.naver.com/webtoon/detail?titleId=803649&no=4&week=sun",
        "imageUrl": "https://image-comic.pstatic.net/webtoon/803649/4/thumbnail_202x120_550bd473-e0b5-4245-9793-8f30ea667a16.jpg",
        "publicationDate": "23.01.07"
    },
    {
        "title": "3화",
        "url": "https://comic.naver.com/webtoon/detail?titleId=803649&no=3&week=sun",
        "imageUrl": "https://image-comic.pstatic.net/webtoon/803649/3/thumbnail_202x120_2c7c477a-7911-40b0-a81e-8aac9d96c59e.jpg",
        "publicationDate": "22.12.31"
    },
    {
        "title": "2화",
        "url": "https://comic.naver.com/webtoon/detail?titleId=803649&no=2&week=sun",
        "imageUrl": "https://image-comic.pstatic.net/webtoon/803649/2/thumbnail_202x120_25280e5c-540b-4701-b10b-e57932b302b7.jpg",
        "publicationDate": "22.12.24"
    },
    {
        "title": "1화",
        "url": "https://comic.naver.com/webtoon/detail?titleId=803649&no=1&week=sun",
        "imageUrl": "https://image-comic.pstatic.net/webtoon/803649/1/thumbnail_202x120_0aa7a3ea-8621-4500-9c2a-381963f885a6.jpg",
        "publicationDate": "22.12.17"
    }
]